[{"sport":"NBA","league":"Draftkings","type":"Classic","about":"Main","games":[{"date":"05/01/2022","day":"Sunday","time":"10:00AM","zone":"ET","filter":""}],"players":[{"name":"Stephen Curry","sal":8900,"fppg":45.78,"pos":"PG","team":"GSW","game":"GSW@MEM 05/01/2022 03:30PM ET","bench":false,"filter":"PG/G/UTIL","mins":34,"rk":4,"val":5.14,"id":"Stephen Curry (22399264)"},{"name":"Giannis Antetokounmpo","sal":11000,"fppg":57.99,"pos":"SF/PF","team":"MIL","game":"MIL@BOS 05/01/2022 01:00PM ET","bench":false,"filter":"SF/PF/F/UTIL","mins":35,"rk":7,"val":5.27,"id":"Giannis Antetokounmpo (22399253)"},{"name":"Jayson Tatum","sal":9400,"fppg":47.47,"pos":"SF/PF","team":"BOS","game":"MIL@BOS 05/01/2022 01:00PM ET","bench":false,"filter":"SF/PF/F/UTIL","mins":37,"rk":18,"val":5.05,"id":"Jayson Tatum (22399260)"},{"name":"Draymond Green","sal":6600,"fppg":31.02,"pos":"PF/C","team":"GSW","game":"GSW@MEM 05/01/2022 03:30PM ET","bench":false,"filter":"PF/C/F/UTIL","mins":33,"rk":26,"val":4.7,"id":"Draymond Green (22399290)"},{"name":"Derrick White","sal":3900,"fppg":27.53,"pos":"PG/SG","team":"BOS","game":"MIL@BOS 05/01/2022 01:00PM ET","bench":false,"filter":"PG/SG/G/UTIL","mins":22,"rk":28,"val":7.06,"id":"Derrick White (22399343)"},{"name":"Jrue Holiday","sal":8200,"fppg":37.84,"pos":"PG","team":"MIL","game":"MIL@BOS 05/01/2022 01:00PM ET","bench":false,"filter":"PG/G/UTIL","mins":34,"rk":32,"val":4.61,"id":"Jrue Holiday (22399267)"},{"name":"Jaren Jackson Jr.","sal":5900,"fppg":31.53,"pos":"PF/C","team":"MEM","game":"GSW@MEM 05/01/2022 03:30PM ET","bench":false,"filter":"PF/C/F/UTIL","mins":25,"rk":40,"val":5.34,"id":"Jaren Jackson Jr. (22399305)"},{"name":"Khris Middleton","sal":7400,"fppg":37.54,"pos":"SF","team":"MIL","game":"MIL@BOS 05/01/2022 01:00PM ET","bench":true,"filter":"SF/F/UTIL","mins":0,"rk":43,"val":5.07,"id":"Khris Middleton (22399275)"},{"name":"Klay Thompson","sal":7100,"fppg":32.89,"pos":"SG/SF","team":"GSW","game":"GSW@MEM 05/01/2022 03:30PM ET","bench":false,"filter":"SG/SF/F/G/UTIL","mins":36,"rk":45,"val":4.63,"id":"Klay Thompson (22399278)"},{"name":"Andrew Wiggins","sal":5600,"fppg":29.81,"pos":"SF/PF","team":"GSW","game":"GSW@MEM 05/01/2022 03:30PM ET","bench":false,"filter":"SF/PF/F/UTIL","mins":32,"rk":46,"val":5.32,"id":"Andrew Wiggins (22399318)"},{"name":"Jordan Poole","sal":6800,"fppg":31.44,"pos":"PG/SG","team":"GSW","game":"GSW@MEM 05/01/2022 03:30PM ET","bench":false,"filter":"PG/SG/G/UTIL","mins":31,"rk":53,"val":4.62,"id":"Jordan Poole (22399286)"},{"name":"Al Horford","sal":5700,"fppg":29.4,"pos":"PF/C","team":"BOS","game":"MIL@BOS 05/01/2022 01:00PM ET","bench":false,"filter":"PF/C/F/UTIL","mins":25,"rk":54,"val":5.16,"id":"Al Horford (22399314)"},{"name":"Dillon Brooks","sal":5800,"fppg":28.55,"pos":"SG/SF","team":"MEM","game":"GSW@MEM 05/01/2022 03:30PM ET","bench":false,"filter":"SG/SF/F/G/UTIL","mins":32,"rk":56,"val":4.92,"id":"Dillon Brooks (22399309)"},{"name":"Marcus Smart","sal":6200,"fppg":29.61,"pos":"PG","team":"BOS","game":"MIL@BOS 05/01/2022 01:00PM ET","bench":false,"filter":"PG/G/UTIL","mins":37,"rk":65,"val":4.78,"id":"Marcus Smart (22399298)"},{"name":"Otto Porter Jr.","sal":3700,"fppg":20.49,"pos":"SF/PF","team":"GSW","game":"GSW@MEM 05/01/2022 03:30PM ET","bench":false,"filter":"SF/PF/F/UTIL","mins":21,"rk":73,"val":5.54,"id":"Otto Porter Jr. (22399351)"},{"name":"Steven Adams","sal":3600,"fppg":26.42,"pos":"C","team":"MEM","game":"GSW@MEM 05/01/2022 03:30PM ET","bench":true,"filter":"C/UTIL","mins":0,"rk":83,"val":7.34,"id":"Steven Adams (22399355)"},{"name":"Pat Connaughton","sal":3900,"fppg":19.97,"pos":"SG","team":"MIL","game":"MIL@BOS 05/01/2022 01:00PM ET","bench":false,"filter":"SG/G/UTIL","mins":23,"rk":89,"val":5.12,"id":"Pat Connaughton (22399340)"},{"name":"Brook Lopez","sal":5300,"fppg":22.51,"pos":"C","team":"MIL","game":"MIL@BOS 05/01/2022 01:00PM ET","bench":false,"filter":"C/UTIL","mins":25,"rk":92,"val":4.25,"id":"Brook Lopez (22399322)"},{"name":"Desmond Bane","sal":6900,"fppg":32.18,"pos":"SG","team":"MEM","game":"GSW@MEM 05/01/2022 03:30PM ET","bench":false,"filter":"SG/G/UTIL","mins":37,"rk":93,"val":4.66,"id":"Desmond Bane (22399283)"},{"name":"Jaylen Brown","sal":7900,"fppg":39.51,"pos":"SG/SF","team":"BOS","game":"MIL@BOS 05/01/2022 01:00PM ET","bench":false,"filter":"SG/SF/F/G/UTIL","mins":37,"rk":123,"val":5,"id":"Jaylen Brown (22399270)"},{"name":"Serge Ibaka","sal":3000,"fppg":14.84,"pos":"PF/C","team":"MIL","game":"MIL@BOS 05/01/2022 01:00PM ET","bench":false,"filter":"PF/C/F/UTIL","mins":4,"rk":128,"val":4.95,"id":"Serge Ibaka (22399436)"},{"name":"Grayson Allen","sal":4800,"fppg":20.5,"pos":"SG/SF","team":"MIL","game":"MIL@BOS 05/01/2022 01:00PM ET","bench":false,"filter":"SG/SF/F/G/UTIL","mins":26,"rk":130,"val":4.27,"id":"Grayson Allen (22399326)"},{"name":"Kevon Looney","sal":3100,"fppg":19.64,"pos":"C","team":"GSW","game":"GSW@MEM 05/01/2022 03:30PM ET","bench":false,"filter":"C/UTIL","mins":14,"rk":133,"val":6.34,"id":"Kevon Looney (22399376)"},{"name":"Grant Williams","sal":3800,"fppg":16.81,"pos":"SF/PF","team":"BOS","game":"MIL@BOS 05/01/2022 01:00PM ET","bench":false,"filter":"SF/PF/F/UTIL","mins":29,"rk":153,"val":4.42,"id":"Grant Williams (22399347)"},{"name":"Nemanja Bjelica","sal":3000,"fppg":16.06,"pos":"C","team":"GSW","game":"GSW@MEM 05/01/2022 03:30PM ET","bench":false,"filter":"C/UTIL","mins":0,"rk":170,"val":5.35,"id":"Nemanja Bjelica (22399412)"},{"name":"George Hill","sal":3000,"fppg":14.88,"pos":"PG","team":"MIL","game":"MIL@BOS 05/01/2022 01:00PM ET","bench":true,"filter":"PG/G/UTIL","mins":0,"rk":171,"val":4.96,"id":"George Hill (22399396)"},{"name":"Kyle Anderson","sal":4100,"fppg":21.03,"pos":"SF/PF","team":"MEM","game":"GSW@MEM 05/01/2022 03:30PM ET","bench":false,"filter":"SF/PF/F/UTIL","mins":18,"rk":176,"val":5.13,"id":"Kyle Anderson (22399331)"},{"name":"Xavier Tillman","sal":3300,"fppg":12.24,"pos":"C","team":"MEM","game":"GSW@MEM 05/01/2022 03:30PM ET","bench":false,"filter":"C/UTIL","mins":0,"rk":177,"val":3.71,"id":"Xavier Tillman (22399368)"},{"name":"Gary Payton II","sal":3400,"fppg":16.15,"pos":"SG","team":"GSW","game":"GSW@MEM 05/01/2022 03:30PM ET","bench":false,"filter":"SG/G/UTIL","mins":16,"rk":191,"val":4.75,"id":"Gary Payton II (22399362)"},{"name":"Andre Iguodala","sal":3000,"fppg":15.83,"pos":"SG/SF","team":"GSW","game":"GSW@MEM 05/01/2022 03:30PM ET","bench":true,"filter":"SG/SF/F/G/UTIL","mins":0,"rk":200,"val":5.28,"id":"Andre Iguodala (22399391)"},{"name":"Ja Morant","sal":9600,"fppg":47.65,"pos":"PG","team":"MEM","game":"GSW@MEM 05/01/2022 03:30PM ET","bench":false,"filter":"PG/G/UTIL","mins":38,"rk":203,"val":4.96,"id":"Ja Morant (22399257)"},{"name":"De'Anthony Melton","sal":3000,"fppg":23.67,"pos":"PG/SG","team":"MEM","game":"GSW@MEM 05/01/2022 03:30PM ET","bench":false,"filter":"PG/SG/G/UTIL","mins":0,"rk":205,"val":7.89,"id":"De'Anthony Melton (22399387)"},{"name":"Sandro Mamukelashvili","sal":3000,"fppg":8.06,"pos":"C","team":"MIL","game":"MIL@BOS 05/01/2022 01:00PM ET","bench":false,"filter":"C/UTIL","mins":0,"rk":206,"val":2.69,"id":"Sandro Mamukelashvili (22399408)"},{"name":"Damion Lee","sal":3000,"fppg":14.25,"pos":"PG","team":"GSW","game":"GSW@MEM 05/01/2022 03:30PM ET","bench":false,"filter":"PG/G/UTIL","mins":0,"rk":216,"val":4.75,"id":"Damion Lee (22399496)"},{"name":"Daniel Theis","sal":4000,"fppg":17.85,"pos":"C","team":"BOS","game":"MIL@BOS 05/01/2022 01:00PM ET","bench":false,"filter":"C/UTIL","mins":9,"rk":223,"val":4.46,"id":"Daniel Theis (22399338)"},{"name":"Tyus Jones","sal":4000,"fppg":20.56,"pos":"PG","team":"MEM","game":"GSW@MEM 05/01/2022 03:30PM ET","bench":false,"filter":"PG/G/UTIL","mins":21,"rk":236,"val":5.14,"id":"Tyus Jones (22399335)"},{"name":"Brandon Clarke","sal":6100,"fppg":23.47,"pos":"PF/C","team":"MEM","game":"GSW@MEM 05/01/2022 03:30PM ET","bench":false,"filter":"PF/C/F/UTIL","mins":31,"rk":237,"val":3.85,"id":"Brandon Clarke (22399301)"},{"name":"Jordan Nwora","sal":3000,"fppg":14.73,"pos":"SF/PF","team":"MIL","game":"MIL@BOS 05/01/2022 01:00PM ET","bench":false,"filter":"SF/PF/F/UTIL","mins":1,"rk":240,"val":4.91,"id":"Jordan Nwora (22399383)"},{"name":"Wesley Matthews","sal":3500,"fppg":10.71,"pos":"SG/SF","team":"MIL","game":"MIL@BOS 05/01/2022 01:00PM ET","bench":false,"filter":"SG/SF/F/G/UTIL","mins":26,"rk":256,"val":3.06,"id":"Wesley Matthews (22399357)"},{"name":"Jon Teske","sal":3000,"fppg":2,"pos":"C","team":"MEM","game":"GSW@MEM 05/01/2022 03:30PM ET","bench":false,"filter":"C/UTIL","mins":0,"rk":265,"val":0.67,"id":"Jon Teske (22399404)"},{"name":"Killian Tillie","sal":3000,"fppg":8.58,"pos":"PF/C","team":"MEM","game":"GSW@MEM 05/01/2022 03:30PM ET","bench":true,"filter":"PF/C/F/UTIL","mins":0,"rk":301,"val":2.86,"id":"Killian Tillie (22399432)"},{"name":"John Konchar","sal":3000,"fppg":14.36,"pos":"SG/SF","team":"MEM","game":"GSW@MEM 05/01/2022 03:30PM ET","bench":false,"filter":"SG/SF/F/G/UTIL","mins":4,"rk":314,"val":4.79,"id":"John Konchar (22399462)"},{"name":"Juan Toscano-Anderson","sal":3000,"fppg":11.08,"pos":"C","team":"GSW","game":"GSW@MEM 05/01/2022 03:30PM ET","bench":false,"filter":"C/UTIL","mins":0,"rk":327,"val":3.69,"id":"Juan Toscano-Anderson (22399410)"},{"name":"Jeff Teague","sal":3000,"fppg":0,"pos":"PG","team":"MIL","game":"MIL@BOS 05/01/2022 01:00PM ET","bench":false,"filter":"PG/G/UTIL","mins":0,"rk":342,"val":0,"id":"Jeff Teague (22399484)"},{"name":"Kelan Martin","sal":3000,"fppg":10.64,"pos":"SF","team":"BOS","game":"MIL@BOS 05/01/2022 01:00PM ET","bench":false,"filter":"SF/F/UTIL","mins":0,"rk":347,"val":3.55,"id":"Kelan Martin (22399550)"},{"name":"Ziaire Williams","sal":3000,"fppg":13.54,"pos":"SF","team":"MEM","game":"GSW@MEM 05/01/2022 03:30PM ET","bench":true,"filter":"SF/F/UTIL","mins":9,"rk":348,"val":4.51,"id":"Ziaire Williams (22399399)"},{"name":"Moses Moody","sal":3000,"fppg":7.69,"pos":"SF","team":"GSW","game":"GSW@MEM 05/01/2022 03:30PM ET","bench":false,"filter":"SF/F/UTIL","mins":0,"rk":349,"val":2.56,"id":"Moses Moody (22399559)"},{"name":"Thanasis Antetokounmpo","sal":3000,"fppg":7.53,"pos":"SF/PF","team":"MIL","game":"MIL@BOS 05/01/2022 01:00PM ET","bench":false,"filter":"SF/PF/F/UTIL","mins":1,"rk":355,"val":2.51,"id":"Thanasis Antetokounmpo (22399424)"},{"name":"Sam Merrill","sal":3000,"fppg":7.04,"pos":"PG/SG","team":"MEM","game":"GSW@MEM 05/01/2022 03:30PM ET","bench":false,"filter":"PG/SG/G/UTIL","mins":0,"rk":374,"val":2.35,"id":"Sam Merrill (22399444)"},{"name":"Santi Aldama","sal":3000,"fppg":9.44,"pos":"PF/C","team":"MEM","game":"GSW@MEM 05/01/2022 03:30PM ET","bench":true,"filter":"PF/C/F/UTIL","mins":0,"rk":376,"val":3.15,"id":"Santi Aldama (22399428)"},{"name":"Aaron Nesmith","sal":3000,"fppg":7.5,"pos":"SG/SF","team":"BOS","game":"MIL@BOS 05/01/2022 01:00PM ET","bench":false,"filter":"SG/SF/F/G/UTIL","mins":0,"rk":380,"val":2.5,"id":"Aaron Nesmith (22399452)"},{"name":"Jonathan Kuminga","sal":3300,"fppg":15.62,"pos":"PF","team":"GSW","game":"GSW@MEM 05/01/2022 03:30PM ET","bench":false,"filter":"PF/F/UTIL","mins":15,"rk":383,"val":4.73,"id":"Jonathan Kuminga (22399365)"},{"name":"Jabari Parker","sal":3000,"fppg":8.92,"pos":"PF","team":"BOS","game":"MIL@BOS 05/01/2022 01:00PM ET","bench":false,"filter":"PF/F/UTIL","mins":0,"rk":398,"val":2.97,"id":"Jabari Parker (22399505)"},{"name":"Jarrett Culver","sal":3000,"fppg":7.81,"pos":"SG/SF","team":"MEM","game":"GSW@MEM 05/01/2022 03:30PM ET","bench":false,"filter":"SG/SF/F/G/UTIL","mins":0,"rk":420,"val":2.6,"id":"Jarrett Culver (22399457)"},{"name":"Chris Chiozza","sal":3000,"fppg":6.71,"pos":"PG","team":"GSW","game":"GSW@MEM 05/01/2022 03:30PM ET","bench":false,"filter":"PG/G/UTIL","mins":0,"rk":424,"val":2.24,"id":"Chris Chiozza (22399493)"},{"name":"Payton Pritchard","sal":3200,"fppg":12.66,"pos":"PG","team":"BOS","game":"MIL@BOS 05/01/2022 01:00PM ET","bench":false,"filter":"PG/G/UTIL","mins":10,"rk":444,"val":3.96,"id":"Payton Pritchard (22399373)"},{"name":"Jevon Carter","sal":3200,"fppg":9.9,"pos":"PG","team":"MIL","game":"MIL@BOS 05/01/2022 01:00PM ET","bench":false,"filter":"PG/G/UTIL","mins":19,"rk":448,"val":3.09,"id":"Jevon Carter (22399370)"},{"name":"Sam Hauser","sal":3000,"fppg":5.03,"pos":"PF","team":"BOS","game":"MIL@BOS 05/01/2022 01:00PM ET","bench":false,"filter":"PF/F/UTIL","mins":0,"rk":467,"val":1.68,"id":"Sam Hauser (22399508)"},{"name":"Malik Fitts","sal":3000,"fppg":3.42,"pos":"SF","team":"BOS","game":"MIL@BOS 05/01/2022 01:00PM ET","bench":false,"filter":"SF/F/UTIL","mins":0,"rk":478,"val":1.14,"id":"Malik Fitts (22399547)"},{"name":"Jalen Lecque","sal":3000,"fppg":0,"pos":"PG","team":"MIL","game":"MIL@BOS 05/01/2022 01:00PM ET","bench":false,"filter":"PG/G/UTIL","mins":0,"rk":1000,"val":0,"id":"Jalen Lecque (22399490)"},{"name":"Al-Farouq Aminu","sal":3000,"fppg":0,"pos":"PF","team":"BOS","game":"MIL@BOS 05/01/2022 01:00PM ET","bench":false,"filter":"PF/F/UTIL","mins":0,"rk":1000,"val":0,"id":"Al-Farouq Aminu (22399511)"},{"name":"Johnny O'Bryant III","sal":3000,"fppg":0,"pos":"PF","team":"MIL","game":"MIL@BOS 05/01/2022 01:00PM ET","bench":false,"filter":"PF/F/UTIL","mins":0,"rk":1000,"val":0,"id":"Johnny O'Bryant III (22399514)"},{"name":"Juhann Begarin","sal":3000,"fppg":0,"pos":"SG","team":"BOS","game":"MIL@BOS 05/01/2022 01:00PM ET","bench":false,"filter":"SG/G/UTIL","mins":0,"rk":1000,"val":0,"id":"Juhann Begarin (22399523)"},{"name":"Elijah Bryant","sal":3000,"fppg":0,"pos":"SG","team":"MIL","game":"MIL@BOS 05/01/2022 01:00PM ET","bench":false,"filter":"SG/G/UTIL","mins":0,"rk":1000,"val":0,"id":"Elijah Bryant (22399535)"},{"name":"C.J. Miles","sal":3000,"fppg":0,"pos":"SF","team":"BOS","game":"MIL@BOS 05/01/2022 01:00PM ET","bench":false,"filter":"SF/F/UTIL","mins":0,"rk":1000,"val":0,"id":"C.J. Miles (22399541)"},{"name":"Marc Gasol","sal":3000,"fppg":0,"pos":"C","team":"MEM","game":"GSW@MEM 05/01/2022 03:30PM ET","bench":false,"filter":"C/UTIL","mins":0,"rk":1000,"val":0,"id":"Marc Gasol (22399378)"},{"name":"James Wiseman","sal":3000,"fppg":0,"pos":"C","team":"GSW","game":"GSW@MEM 05/01/2022 03:30PM ET","bench":true,"filter":"C/UTIL","mins":0,"rk":1000,"val":0,"id":"James Wiseman (22399414)"},{"name":"Romeo Weems","sal":3000,"fppg":0,"pos":"SF/PF","team":"MEM","game":"GSW@MEM 05/01/2022 03:30PM ET","bench":false,"filter":"SF/PF/F/UTIL","mins":0,"rk":1000,"val":0,"id":"Romeo Weems (22399416)"},{"name":"Matthew Hurt","sal":3000,"fppg":0,"pos":"SF/PF","team":"MEM","game":"GSW@MEM 05/01/2022 03:30PM ET","bench":false,"filter":"SF/PF/F/UTIL","mins":0,"rk":1000,"val":0,"id":"Matthew Hurt (22399420)"},{"name":"LJ Figueroa","sal":3000,"fppg":0,"pos":"SG/SF","team":"GSW","game":"GSW@MEM 05/01/2022 03:30PM ET","bench":false,"filter":"SG/SF/F/G/UTIL","mins":0,"rk":1000,"val":0,"id":"LJ Figueroa (22399467)"},{"name":"David Stockton","sal":3000,"fppg":0,"pos":"PG","team":"MEM","game":"GSW@MEM 05/01/2022 03:30PM ET","bench":false,"filter":"PG/G/UTIL","mins":0,"rk":1000,"val":0,"id":"David Stockton (22399475)"},{"name":"Nico Mannion","sal":3000,"fppg":0,"pos":"PG","team":"GSW","game":"GSW@MEM 05/01/2022 03:30PM ET","bench":false,"filter":"PG/G/UTIL","mins":0,"rk":1000,"val":0,"id":"Nico Mannion (22399499)"},{"name":"Alen Smailagic","sal":3000,"fppg":0,"pos":"PF","team":"GSW","game":"GSW@MEM 05/01/2022 03:30PM ET","bench":false,"filter":"PF/F/UTIL","mins":0,"rk":1000,"val":0,"id":"Alen Smailagic (22399517)"},{"name":"Sean McDermott","sal":3000,"fppg":0,"pos":"SG","team":"MEM","game":"GSW@MEM 05/01/2022 03:30PM ET","bench":false,"filter":"SG/G/UTIL","mins":0,"rk":1000,"val":0,"id":"Sean McDermott (22399529)"},{"name":"Axel Toupane","sal":3000,"fppg":0,"pos":"SF","team":"GSW","game":"GSW@MEM 05/01/2022 03:30PM ET","bench":false,"filter":"SF/F/UTIL","mins":0,"rk":1000,"val":0,"id":"Axel Toupane (22399562)"},{"name":"Tyrell Terry","sal":3000,"fppg":1,"pos":"PG/SG","team":"MEM","game":"GSW@MEM 05/01/2022 03:30PM ET","bench":false,"filter":"PG/SG/G/UTIL","mins":0,"rk":1000,"val":0.33,"id":"Tyrell Terry (22399440)"},{"name":"Joe Johnson","sal":3000,"fppg":2,"pos":"SF","team":"BOS","game":"MIL@BOS 05/01/2022 01:00PM ET","bench":false,"filter":"SF/F/UTIL","mins":0,"rk":1000,"val":0.67,"id":"Joe Johnson (22399538)"},{"name":"DaQuan Jeffries","sal":3000,"fppg":2,"pos":"SG","team":"MEM","game":"GSW@MEM 05/01/2022 03:30PM ET","bench":false,"filter":"SG/G/UTIL","mins":0,"rk":1000,"val":0.67,"id":"DaQuan Jeffries (22399532)"},{"name":"Dakota Mathias","sal":3000,"fppg":2.17,"pos":"PG","team":"MEM","game":"GSW@MEM 05/01/2022 03:30PM ET","bench":false,"filter":"PG/G/UTIL","mins":0,"rk":1000,"val":0.72,"id":"Dakota Mathias (22399481)"},{"name":"Javin DeLaurier","sal":3000,"fppg":3.25,"pos":"C","team":"MIL","game":"MIL@BOS 05/01/2022 01:00PM ET","bench":false,"filter":"C/UTIL","mins":0,"rk":1000,"val":1.08,"id":"Javin DeLaurier (22399406)"},{"name":"Nik Stauskas","sal":3000,"fppg":3.28,"pos":"SG","team":"BOS","game":"MIL@BOS 05/01/2022 01:00PM ET","bench":false,"filter":"SG/G/UTIL","mins":0,"rk":1000,"val":1.09,"id":"Nik Stauskas (22399520)"},{"name":"Yves Pons","sal":3000,"fppg":3.38,"pos":"SF","team":"MEM","game":"GSW@MEM 05/01/2022 03:30PM ET","bench":false,"filter":"SF/F/UTIL","mins":0,"rk":1000,"val":1.13,"id":"Yves Pons (22399553)"},{"name":"Justin Jackson","sal":3000,"fppg":3.96,"pos":"SF","team":"BOS","game":"MIL@BOS 05/01/2022 01:00PM ET","bench":false,"filter":"SF/F/UTIL","mins":0,"rk":1000,"val":1.32,"id":"Justin Jackson (22399565)"},{"name":"Shaq Buchanan","sal":3000,"fppg":4.25,"pos":"PG","team":"MEM","game":"GSW@MEM 05/01/2022 03:30PM ET","bench":false,"filter":"PG/G/UTIL","mins":0,"rk":1000,"val":1.42,"id":"Shaq Buchanan (22399478)"},{"name":"Brodric Thomas","sal":3000,"fppg":4.33,"pos":"PG","team":"BOS","game":"MIL@BOS 05/01/2022 01:00PM ET","bench":false,"filter":"PG/G/UTIL","mins":0,"rk":1000,"val":1.44,"id":"Brodric Thomas (22399472)"},{"name":"Quinndary Weatherspoon","sal":3000,"fppg":5.27,"pos":"PG","team":"GSW","game":"GSW@MEM 05/01/2022 03:30PM ET","bench":false,"filter":"PG/G/UTIL","mins":0,"rk":1000,"val":1.76,"id":"Quinndary Weatherspoon (22399502)"},{"name":"Matt Ryan","sal":3000,"fppg":5.5,"pos":"SF","team":"BOS","game":"MIL@BOS 05/01/2022 01:00PM ET","bench":false,"filter":"SF/F/UTIL","mins":0,"rk":1000,"val":1.83,"id":"Matt Ryan (22399544)"},{"name":"Luke Kornet","sal":3000,"fppg":6.12,"pos":"C","team":"BOS","game":"MIL@BOS 05/01/2022 01:00PM ET","bench":false,"filter":"C/UTIL","mins":0,"rk":1000,"val":2.04,"id":"Luke Kornet (22399402)"},{"name":"Luca Vildoza","sal":3000,"fppg":6.62,"pos":"PG/SG","team":"MIL","game":"MIL@BOS 05/01/2022 01:00PM ET","bench":false,"filter":"PG/SG/G/UTIL","mins":3,"rk":1000,"val":2.21,"id":"Luca Vildoza (22399448)"},{"name":"Rayjon Tucker","sal":3000,"fppg":7.25,"pos":"SF","team":"MIL","game":"MIL@BOS 05/01/2022 01:00PM ET","bench":false,"filter":"SF/F/UTIL","mins":0,"rk":1000,"val":2.42,"id":"Rayjon Tucker (22399380)"},{"name":"Lindell Wigginton","sal":3000,"fppg":8.22,"pos":"PG","team":"MIL","game":"MIL@BOS 05/01/2022 01:00PM ET","bench":false,"filter":"PG/G/UTIL","mins":0,"rk":1000,"val":2.74,"id":"Lindell Wigginton (22399487)"},{"name":"Shaquille Harrison","sal":3000,"fppg":8.25,"pos":"SG","team":"MEM","game":"GSW@MEM 05/01/2022 03:30PM ET","bench":false,"filter":"SG/G/UTIL","mins":0,"rk":1000,"val":2.75,"id":"Shaquille Harrison (22399526)"},{"name":"DeAndre' Bembry","sal":3000,"fppg":12.98,"pos":"SF","team":"MIL","game":"MIL@BOS 05/01/2022 01:00PM ET","bench":false,"filter":"SF/F/UTIL","mins":0,"rk":1000,"val":4.33,"id":"DeAndre' Bembry (22399556)"},{"name":"Bobby Portis","sal":6400,"fppg":31.34,"pos":"PF/C","team":"MIL","game":"MIL@BOS 05/01/2022 01:00PM ET","bench":false,"filter":"PF/C/F/UTIL","mins":31,"rk":1000,"val":4.9,"id":"Bobby Portis (22399294)"},{"name":"Robert Williams","sal":5000,"fppg":30.66,"pos":"C","team":"BOS","game":"MIL@BOS 05/01/2022 01:00PM ET","bench":false,"filter":"C/UTIL","mins":0,"rk":1000,"val":6.13,"id":"Robert Williams (22399324)"}]},{"sport":"NBA","league":"FanDuel","type":"Classic","about":"Main","games":[{"date":"05/01/2022","day":"Sunday","time":"10:00AM","zone":"ET","filter":""}],"players":[{"Player ID + Player Name":"75484-40199:Giannis Antetokounmpo","Id":"75484-40199","":"","Roster Position":"SF/PF","name":"Giannis Antetokounmpo","sal":11800,"fppg":56.55,"pos":"PF/SF","team":"MIL","game":"MIL@BOS 05/01/2022 01:00PM ET","bench":false,"filter":"SF/PF/F/UTIL","mins":35,"rk":7,"val":4.79},{"Player ID + Player Name":"75484-80808:Jayson Tatum","Id":"75484-80808","":"","Roster Position":"SF/PF","name":"Jayson Tatum","sal":10300,"fppg":45.05,"pos":"SF/PF","team":"BOS","game":"MIL@BOS 05/01/2022 01:00PM ET","bench":false,"filter":"SF/PF/F/UTIL","mins":37,"rk":18,"val":4.37},{"Player ID + Player Name":"75484-110344:Ja Morant","Id":"75484-110344","":"","Roster Position":"PG","name":"Ja Morant","sal":10000,"fppg":45.46,"pos":"PG","team":"MEM","game":"GSW@MEM 05/01/2022 03:30PM ET","bench":false,"filter":"PG/G/UTIL","mins":38,"rk":203,"val":4.55},{"Player ID + Player Name":"75484-9524:Stephen Curry","Id":"75484-9524","":"","Roster Position":"PG","name":"Stephen Curry","sal":9500,"fppg":43.37,"pos":"PG","team":"GS","game":"GSW@MEM 05/01/2022 03:30PM ET","bench":false,"filter":"PG/G/UTIL","mins":34,"rk":4,"val":4.57},{"Player ID + Player Name":"75484-9663:Jrue Holiday","Id":"75484-9663","":"","Roster Position":"PG/SG","name":"Jrue Holiday","sal":8100,"fppg":36.95,"pos":"PG/SG","team":"MIL","game":"MIL@BOS 05/01/2022 01:00PM ET","bench":false,"filter":"PG/G/UTIL","mins":34,"rk":32,"val":4.56},{"Player ID + Player Name":"75484-67026:Jaylen Brown","Id":"75484-67026","":"","Roster Position":"SG/SF","name":"Jaylen Brown","sal":7900,"fppg":37.76,"pos":"SF/SG","team":"BOS","game":"MIL@BOS 05/01/2022 01:00PM ET","bench":false,"filter":"SG/SF/F/G/UTIL","mins":37,"rk":123,"val":4.78},{"Player ID + Player Name":"75484-16261:Khris Middleton","Id":"75484-16261","":"","Roster Position":"SG/SF","name":"Khris Middleton","sal":7500,"fppg":35.55,"pos":"SF/SG","team":"MIL","game":"MIL@BOS 05/01/2022 01:00PM ET","bench":true,"filter":"SF/F/UTIL","mins":0,"rk":43,"val":4.74},{"Player ID + Player Name":"75484-145334:Desmond Bane","Id":"75484-145334","":"","Roster Position":"SG/SF","name":"Desmond Bane","sal":7300,"fppg":31.27,"pos":"SG/SF","team":"MEM","game":"GSW@MEM 05/01/2022 03:30PM ET","bench":false,"filter":"SG/G/UTIL","mins":37,"rk":93,"val":4.28},{"Player ID + Player Name":"75484-15860:Draymond Green","Id":"75484-15860","":"","Roster Position":"PF/C","name":"Draymond Green","sal":7000,"fppg":31.3,"pos":"PF/C","team":"GS","game":"GSW@MEM 05/01/2022 03:30PM ET","bench":false,"filter":"PF/C/F/UTIL","mins":33,"rk":26,"val":4.47},{"Player ID + Player Name":"75484-110322:Jordan Poole","Id":"75484-110322","":"","Roster Position":"PG/SG","name":"Jordan Poole","sal":6800,"fppg":29.75,"pos":"PG/SG","team":"GS","game":"GSW@MEM 05/01/2022 03:30PM ET","bench":false,"filter":"PG/SG/G/UTIL","mins":31,"rk":53,"val":4.38},{"Player ID + Player Name":"75484-14509:Klay Thompson","Id":"75484-14509","":"","Roster Position":"SG","name":"Klay Thompson","sal":6500,"fppg":31.36,"pos":"SG","team":"GS","game":"GSW@MEM 05/01/2022 03:30PM ET","bench":false,"filter":"SG/SF/F/G/UTIL","mins":36,"rk":45,"val":4.82},{"Player ID + Player Name":"75484-23670:Marcus Smart","Id":"75484-23670","":"","Roster Position":"PG/SG","name":"Marcus Smart","sal":6300,"fppg":29.26,"pos":"SG/PG","team":"BOS","game":"MIL@BOS 05/01/2022 01:00PM ET","bench":false,"filter":"PG/G/UTIL","mins":37,"rk":65,"val":4.64},{"Player ID + Player Name":"75484-42156:Bobby Portis","Id":"75484-42156","":"","Roster Position":"PF/C","name":"Bobby Portis","sal":6200,"fppg":30.15,"pos":"PF/C","team":"MIL","game":"MIL@BOS 05/01/2022 01:00PM ET","bench":false,"filter":"PF/C/F/UTIL","mins":31,"rk":1000,"val":4.86},{"Player ID + Player Name":"75484-84683:Jaren Jackson","Id":"75484-84683","":"","Roster Position":"PF/C","name":"Jaren Jackson","sal":6100,"fppg":32.65,"pos":"PF/C","team":"MEM","game":"GS@MEM undefined","bench":false,"filter":"PF/C","mins":0,"rk":1000,"val":5.35},{"Player ID + Player Name":"75484-49116:Andrew Wiggins","Id":"75484-49116","":"","Roster Position":"SG/SF","name":"Andrew Wiggins","sal":6000,"fppg":29.3,"pos":"SF/SG","team":"GS","game":"GSW@MEM 05/01/2022 03:30PM ET","bench":false,"filter":"SF/PF/F/UTIL","mins":32,"rk":46,"val":4.88},{"Player ID + Player Name":"75484-110353:Brandon Clarke","Id":"75484-110353","":"","Roster Position":"PF/C","name":"Brandon Clarke","sal":5900,"fppg":24.42,"pos":"PF/C","team":"MEM","game":"GSW@MEM 05/01/2022 03:30PM ET","bench":false,"filter":"PF/C/F/UTIL","mins":31,"rk":237,"val":4.14},{"Player ID + Player Name":"75484-84711:Grayson Allen","Id":"75484-84711","":"","Roster Position":"SG/SF","name":"Grayson Allen","sal":5600,"fppg":19.79,"pos":"SG/SF","team":"MIL","game":"MIL@BOS 05/01/2022 01:00PM ET","bench":false,"filter":"SG/SF/F/G/UTIL","mins":26,"rk":130,"val":3.53},{"Player ID + Player Name":"75484-9453:Al Horford","Id":"75484-9453","":"","Roster Position":"PF/C","name":"Al Horford","sal":5300,"fppg":29.56,"pos":"PF/C","team":"BOS","game":"MIL@BOS 05/01/2022 01:00PM ET","bench":false,"filter":"PF/C/F/UTIL","mins":25,"rk":54,"val":5.58},{"Player ID + Player Name":"75484-60233:Dillon Brooks","Id":"75484-60233","":"","Roster Position":"SG/SF","name":"Dillon Brooks","sal":5200,"fppg":28.06,"pos":"SG/SF","team":"MEM","game":"GSW@MEM 05/01/2022 03:30PM ET","bench":false,"filter":"SG/SF/F/G/UTIL","mins":32,"rk":56,"val":5.4},{"Player ID + Player Name":"75484-9621:Brook Lopez","Id":"75484-9621","":"","Roster Position":"C","name":"Brook Lopez","sal":5100,"fppg":23,"pos":"C","team":"MIL","game":"MIL@BOS 05/01/2022 01:00PM ET","bench":false,"filter":"C/UTIL","mins":25,"rk":92,"val":4.51},{"Player ID + Player Name":"75484-84708:Robert Williams","Id":"75484-84708","":"","Roster Position":"PF/C","name":"Robert Williams","sal":4900,"fppg":32.08,"pos":"PF/C","team":"BOS","game":"MIL@BOS 05/01/2022 01:00PM ET","bench":false,"filter":"C/UTIL","mins":0,"rk":1000,"val":6.55},{"Player ID + Player Name":"75484-23169:Steven Adams","Id":"75484-23169","":"","Roster Position":"C","name":"Steven Adams","sal":4700,"fppg":26.52,"pos":"C","team":"MEM","game":"GSW@MEM 05/01/2022 03:30PM ET","bench":true,"filter":"C/UTIL","mins":0,"rk":83,"val":5.64},{"Player ID + Player Name":"75484-110318:Grant Williams","Id":"75484-110318","":"","Roster Position":"PF","name":"Grant Williams","sal":4400,"fppg":16.77,"pos":"PF","team":"BOS","game":"MIL@BOS 05/01/2022 01:00PM ET","bench":false,"filter":"SF/PF/F/UTIL","mins":29,"rk":153,"val":3.81},{"Player ID + Player Name":"75484-58081:Tyus Jones","Id":"75484-58081","":"","Roster Position":"PG","name":"Tyus Jones","sal":4300,"fppg":20.43,"pos":"PG","team":"MEM","game":"GSW@MEM 05/01/2022 03:30PM ET","bench":false,"filter":"PG/G/UTIL","mins":21,"rk":236,"val":4.75},{"Player ID + Player Name":"75484-15993:Pat Connaughton","Id":"75484-15993","":"","Roster Position":"SF/PF","name":"Pat Connaughton","sal":4200,"fppg":19.48,"pos":"SF/PF","team":"MIL","game":"MIL@BOS 05/01/2022 01:00PM ET","bench":false,"filter":"SG/G/UTIL","mins":23,"rk":89,"val":4.64},{"Player ID + Player Name":"75484-49675:Derrick White","Id":"75484-49675","":"","Roster Position":"PG","name":"Derrick White","sal":4100,"fppg":27.4,"pos":"PG","team":"BOS","game":"MIL@BOS 05/01/2022 01:00PM ET","bench":false,"filter":"PG/SG/G/UTIL","mins":22,"rk":28,"val":6.68},{"Player ID + Player Name":"75484-81529:Daniel Theis","Id":"75484-81529","":"","Roster Position":"PF/C","name":"Daniel Theis","sal":4000,"fppg":17.76,"pos":"PF/C","team":"BOS","game":"MIL@BOS 05/01/2022 01:00PM ET","bench":false,"filter":"C/UTIL","mins":9,"rk":223,"val":4.44},{"Player ID + Player Name":"75484-15628:Otto Porter","Id":"75484-15628","":"","Roster Position":"SF/PF","name":"Otto Porter","sal":3900,"fppg":20.69,"pos":"SF/PF","team":"GS","game":"GS@MEM undefined","bench":false,"filter":"SF/PF","mins":0,"rk":1000,"val":5.31},{"Player ID + Player Name":"75484-23716:Kyle Anderson","Id":"75484-23716","":"","Roster Position":"SF/PF","name":"Kyle Anderson","sal":3900,"fppg":21.74,"pos":"SF/PF","team":"MEM","game":"GSW@MEM 05/01/2022 03:30PM ET","bench":false,"filter":"SF/PF/F/UTIL","mins":18,"rk":176,"val":5.57},{"Player ID + Player Name":"75484-58519:Gary Payton","Id":"75484-58519","":"","Roster Position":"SG","name":"Gary Payton","sal":3800,"fppg":17,"pos":"SG","team":"GS","game":"GS@MEM undefined","bench":false,"filter":"SG","mins":0,"rk":1000,"val":4.47},{"Player ID + Player Name":"75484-9799:Wesley Matthews","Id":"75484-9799","":"","Roster Position":"SG","name":"Wesley Matthews","sal":3800,"fppg":10.54,"pos":"SG","team":"MIL","game":"MIL@BOS 05/01/2022 01:00PM ET","bench":false,"filter":"SG/SF/F/G/UTIL","mins":26,"rk":256,"val":2.77},{"Player ID + Player Name":"75484-145335:Payton Pritchard","Id":"75484-145335","":"","Roster Position":"PG/SG","name":"Payton Pritchard","sal":3700,"fppg":12.02,"pos":"PG/SG","team":"BOS","game":"MIL@BOS 05/01/2022 01:00PM ET","bench":false,"filter":"PG/G/UTIL","mins":10,"rk":444,"val":3.25},{"Player ID + Player Name":"75484-84696:Jevon Carter","Id":"75484-84696","":"","Roster Position":"PG/SG","name":"Jevon Carter","sal":3700,"fppg":9.7,"pos":"PG/SG","team":"MIL","game":"MIL@BOS 05/01/2022 01:00PM ET","bench":false,"filter":"PG/G/UTIL","mins":19,"rk":448,"val":2.62},{"Player ID + Player Name":"75484-145336:Xavier Tillman","Id":"75484-145336","":"","Roster Position":"PF","name":"Xavier Tillman","sal":3600,"fppg":12.77,"pos":"PF","team":"MEM","game":"GSW@MEM 05/01/2022 03:30PM ET","bench":false,"filter":"C/UTIL","mins":0,"rk":177,"val":3.55},{"Player ID + Player Name":"75484-58576:Kevon Looney","Id":"75484-58576","":"","Roster Position":"PF/C","name":"Kevon Looney","sal":3600,"fppg":19.99,"pos":"C/PF","team":"GS","game":"GSW@MEM 05/01/2022 03:30PM ET","bench":false,"filter":"C/UTIL","mins":14,"rk":133,"val":5.55},{"Player ID + Player Name":"75484-9703:George Hill","Id":"75484-9703","":"","Roster Position":"PG","name":"George Hill","sal":3600,"fppg":14.87,"pos":"PG","team":"MIL","game":"MIL@BOS 05/01/2022 01:00PM ET","bench":true,"filter":"PG/G/UTIL","mins":0,"rk":171,"val":4.13},{"Player ID + Player Name":"75484-158854:Sam Hauser","Id":"75484-158854","":"","Roster Position":"PF","name":"Sam Hauser","sal":3500,"fppg":4.68,"pos":"PF","team":"BOS","game":"MIL@BOS 05/01/2022 01:00PM ET","bench":false,"filter":"PF/F/UTIL","mins":0,"rk":467,"val":1.34},{"Player ID + Player Name":"75484-110348:Quinndary Weatherspoon","Id":"75484-110348","":"","Roster Position":"SG","name":"Quinndary Weatherspoon","sal":3500,"fppg":5.21,"pos":"SG","team":"GS","game":"GSW@MEM 05/01/2022 03:30PM ET","bench":false,"filter":"PG/G/UTIL","mins":0,"rk":1000,"val":1.49},{"Player ID + Player Name":"75484-111372:Thanasis Antetokounmpo","Id":"75484-111372","":"","Roster Position":"SF/PF","name":"Thanasis Antetokounmpo","sal":3500,"fppg":7.73,"pos":"SF/PF","team":"MIL","game":"MIL@BOS 05/01/2022 01:00PM ET","bench":false,"filter":"SF/PF/F/UTIL","mins":1,"rk":355,"val":2.21},{"Player ID + Player Name":"75484-111376:John Konchar","Id":"75484-111376","":"","Roster Position":"SG/SF","name":"John Konchar","sal":3500,"fppg":14.4,"pos":"SF/SG","team":"MEM","game":"GSW@MEM 05/01/2022 03:30PM ET","bench":false,"filter":"SG/SF/F/G/UTIL","mins":4,"rk":314,"val":4.12},{"Player ID + Player Name":"75484-157843:Ziaire Williams","Id":"75484-157843","":"","Roster Position":"SF","name":"Ziaire Williams","sal":3500,"fppg":13.28,"pos":"SF","team":"MEM","game":"GSW@MEM 05/01/2022 03:30PM ET","bench":true,"filter":"SF/F/UTIL","mins":9,"rk":348,"val":3.8},{"Player ID + Player Name":"75484-117779:Juan Toscano-Anderson","Id":"75484-117779","":"","Roster Position":"SF/PF","name":"Juan Toscano-Anderson","sal":3500,"fppg":11.19,"pos":"SF/PF","team":"GS","game":"GSW@MEM 05/01/2022 03:30PM ET","bench":false,"filter":"C/UTIL","mins":0,"rk":327,"val":3.2},{"Player ID + Player Name":"75484-157846:Sandro Mamukelashvili","Id":"75484-157846","":"","Roster Position":"PF/C","name":"Sandro Mamukelashvili","sal":3500,"fppg":7.91,"pos":"PF/C","team":"MIL","game":"MIL@BOS 05/01/2022 01:00PM ET","bench":false,"filter":"C/UTIL","mins":0,"rk":206,"val":2.26},{"Player ID + Player Name":"75484-157844:Santi Aldama","Id":"75484-157844","":"","Roster Position":"PF","name":"Santi Aldama","sal":3500,"fppg":9.37,"pos":"PF","team":"MEM","game":"GSW@MEM 05/01/2022 03:30PM ET","bench":true,"filter":"PF/C/F/UTIL","mins":0,"rk":376,"val":2.68},{"Player ID + Player Name":"75484-145313:Jordan Nwora","Id":"75484-145313","":"","Roster Position":"SF/PF","name":"Jordan Nwora","sal":3500,"fppg":14.09,"pos":"PF/SF","team":"MIL","game":"MIL@BOS 05/01/2022 01:00PM ET","bench":false,"filter":"SF/PF/F/UTIL","mins":1,"rk":240,"val":4.03},{"Player ID + Player Name":"75484-145825:Malik Fitts","Id":"75484-145825","":"","Roster Position":"PF","name":"Malik Fitts","sal":3500,"fppg":3.13,"pos":"PF","team":"BOS","game":"MIL@BOS 05/01/2022 01:00PM ET","bench":false,"filter":"SF/F/UTIL","mins":0,"rk":478,"val":0.89},{"Player ID + Player Name":"75484-116906:Lindell Wigginton","Id":"75484-116906","":"","Roster Position":"PG","name":"Lindell Wigginton","sal":3500,"fppg":7.92,"pos":"PG","team":"MIL","game":"MIL@BOS 05/01/2022 01:00PM ET","bench":false,"filter":"PG/G/UTIL","mins":0,"rk":1000,"val":2.26},{"Player ID + Player Name":"75484-145326:Tyrell Terry","Id":"75484-145326","":"","Roster Position":"PG","name":"Tyrell Terry","sal":3500,"fppg":1,"pos":"PG","team":"MEM","game":"GSW@MEM 05/01/2022 03:30PM ET","bench":false,"filter":"PG/SG/G/UTIL","mins":0,"rk":1000,"val":0.29},{"Player ID + Player Name":"75484-145333:Aaron Nesmith","Id":"75484-145333","":"","Roster Position":"SG","name":"Aaron Nesmith","sal":3500,"fppg":7.3,"pos":"SG","team":"BOS","game":"MIL@BOS 05/01/2022 01:00PM ET","bench":false,"filter":"SG/SF/F/G/UTIL","mins":0,"rk":380,"val":2.09},{"Player ID + Player Name":"75484-9664:Andre Iguodala","Id":"75484-9664","":"","Roster Position":"SG/SF","name":"Andre Iguodala","sal":3500,"fppg":16.47,"pos":"SF/SG","team":"GS","game":"GSW@MEM 05/01/2022 03:30PM ET","bench":true,"filter":"SG/SF/F/G/UTIL","mins":0,"rk":200,"val":4.71},{"Player ID + Player Name":"75484-145347:James Wiseman","Id":"75484-145347","":"","Roster Position":"C","name":"James Wiseman","sal":3500,"fppg":21.52,"pos":"C","team":"GS","game":"GSW@MEM 05/01/2022 03:30PM ET","bench":true,"filter":"C/UTIL","mins":0,"rk":1000,"val":6.15},{"Player ID + Player Name":"75484-18376:Damion Lee","Id":"75484-18376","":"","Roster Position":"SG","name":"Damion Lee","sal":3500,"fppg":14.01,"pos":"SG","team":"GS","game":"GSW@MEM 05/01/2022 03:30PM ET","bench":false,"filter":"PG/G/UTIL","mins":0,"rk":216,"val":4},{"Player ID + Player Name":"75484-145737:Brodric Thomas","Id":"75484-145737","":"","Roster Position":"SG","name":"Brodric Thomas","sal":3500,"fppg":4.13,"pos":"SG","team":"BOS","game":"MIL@BOS 05/01/2022 01:00PM ET","bench":false,"filter":"PG/G/UTIL","mins":0,"rk":1000,"val":1.18},{"Player ID + Player Name":"75484-12368:Nemanja Bjelica","Id":"75484-12368","":"","Roster Position":"PF","name":"Nemanja Bjelica","sal":3500,"fppg":15.79,"pos":"PF","team":"GS","game":"GSW@MEM 05/01/2022 03:30PM ET","bench":false,"filter":"C/UTIL","mins":0,"rk":170,"val":4.51},{"Player ID + Player Name":"75484-157904:Jonathan Kuminga","Id":"75484-157904","":"","Roster Position":"SF","name":"Jonathan Kuminga","sal":3500,"fppg":15.3,"pos":"SF","team":"GS","game":"GSW@MEM 05/01/2022 03:30PM ET","bench":false,"filter":"PF/F/UTIL","mins":15,"rk":383,"val":4.37},{"Player ID + Player Name":"75484-116178:Rayjon Tucker","Id":"75484-116178","":"","Roster Position":"PG","name":"Rayjon Tucker","sal":3500,"fppg":7.38,"pos":"PG","team":"MIL","game":"MIL@BOS 05/01/2022 01:00PM ET","bench":false,"filter":"SF/F/UTIL","mins":0,"rk":1000,"val":2.11},{"Player ID + Player Name":"75484-159064:Yves Pons","Id":"75484-159064","":"","Roster Position":"SF","name":"Yves Pons","sal":3500,"fppg":3.58,"pos":"SF","team":"MEM","game":"GSW@MEM 05/01/2022 03:30PM ET","bench":false,"filter":"SF/F/UTIL","mins":0,"rk":1000,"val":1.02},{"Player ID + Player Name":"75484-84703:De'Anthony Melton","Id":"75484-84703","":"","Roster Position":"PG/SG","name":"De'Anthony Melton","sal":3500,"fppg":23.63,"pos":"SG/PG","team":"MEM","game":"GSW@MEM 05/01/2022 03:30PM ET","bench":false,"filter":"PG/SG/G/UTIL","mins":0,"rk":205,"val":6.75},{"Player ID + Player Name":"75484-145632:Killian Tillie","Id":"75484-145632","":"","Roster Position":"PF","name":"Killian Tillie","sal":3500,"fppg":9,"pos":"PF","team":"MEM","game":"GSW@MEM 05/01/2022 03:30PM ET","bench":true,"filter":"PF/C/F/UTIL","mins":0,"rk":301,"val":2.57},{"Player ID + Player Name":"75484-9957:Serge Ibaka","Id":"75484-9957","":"","Roster Position":"PF/C","name":"Serge Ibaka","sal":3500,"fppg":14.59,"pos":"PF/C","team":"MIL","game":"MIL@BOS 05/01/2022 01:00PM ET","bench":false,"filter":"PF/C/F/UTIL","mins":4,"rk":128,"val":4.17},{"Player ID + Player Name":"75484-157802:Moses Moody","Id":"75484-157802","":"","Roster Position":"SG","name":"Moses Moody","sal":3500,"fppg":7.45,"pos":"SG","team":"GS","game":"GSW@MEM 05/01/2022 03:30PM ET","bench":false,"filter":"SF/F/UTIL","mins":0,"rk":349,"val":2.13},{"Player ID + Player Name":"75484-162411:Matt Ryan","Id":"75484-162411","":"","Roster Position":"SF","name":"Matt Ryan","sal":3500,"fppg":6,"pos":"SF","team":"BOS","game":"MIL@BOS 05/01/2022 01:00PM ET","bench":false,"filter":"SF/F/UTIL","mins":0,"rk":1000,"val":1.71},{"Player ID + Player Name":"75484-149736:Luca Vildoza","Id":"75484-149736","":"","Roster Position":"PG","name":"Luca Vildoza","sal":3500,"fppg":7.35,"pos":"PG","team":"MIL","game":"MIL@BOS 05/01/2022 01:00PM ET","bench":false,"filter":"PG/SG/G/UTIL","mins":3,"rk":1000,"val":2.1},{"Player ID + Player Name":"75484-23801:Nik Stauskas","Id":"75484-23801","":"","Roster Position":"SG","name":"Nik Stauskas","sal":3500,"fppg":2.95,"pos":"SG","team":"BOS","game":"MIL@BOS 05/01/2022 01:00PM ET","bench":false,"filter":"SG/G/UTIL","mins":0,"rk":1000,"val":0.84},{"Player ID + Player Name":"75484-41083:Luke Kornet","Id":"75484-41083","":"","Roster Position":"PF","name":"Luke Kornet","sal":3500,"fppg":6.42,"pos":"PF","team":"BOS","game":"MIL@BOS 05/01/2022 01:00PM ET","bench":false,"filter":"C/UTIL","mins":0,"rk":1000,"val":1.83},{"Player ID + Player Name":"75484-97018:Chris Chiozza","Id":"75484-97018","":"","Roster Position":"PG","name":"Chris Chiozza","sal":3500,"fppg":6.31,"pos":"PG","team":"GS","game":"GSW@MEM 05/01/2022 03:30PM ET","bench":false,"filter":"PG/G/UTIL","mins":0,"rk":424,"val":1.8},{"Player ID + Player Name":"75484-110333:Jarrett Culver","Id":"75484-110333","":"","Roster Position":"SG/SF","name":"Jarrett Culver","sal":3500,"fppg":8.03,"pos":"SF/SG","team":"MEM","game":"GSW@MEM 05/01/2022 03:30PM ET","bench":false,"filter":"SG/SF/F/G/UTIL","mins":0,"rk":420,"val":2.29}]},{"sport":"NBA","league":"Yahoo","type":"Classic","about":"Main","games":[{"date":"05/01/2022","day":"Sunday","time":"10:00AM","zone":"ET","filter":""}],"players":[{"name":"Khris Middleton","sal":10,"fppg":35.9,"pos":"SF","team":"MIL","game":"MIL@BOS 1:00PM EDT","bench":true,"filter":"SF/F/UTIL","mins":0,"rk":43,"val":3590,"id":"nba.p.5073$nba.g.2447590 - Khris Middleton"},{"name":"Giannis Antetokounmpo","sal":57,"fppg":56.4,"pos":"PF","team":"MIL","game":"MIL@BOS 1:00PM EDT","bench":false,"filter":"SF/PF/F/UTIL","mins":35,"rk":7,"val":989.47,"id":"nba.p.5185$nba.g.2447590 - Giannis Antetokounmpo"},{"name":"Thanasis Antetokounmpo","sal":10,"fppg":7.7,"pos":"SF","team":"MIL","game":"MIL@BOS 1:00PM EDT","bench":false,"filter":"SF/PF/F/UTIL","mins":1,"rk":355,"val":770,"id":"nba.p.5362$nba.g.2447590 - Thanasis Antetokounmpo"},{"name":"Bobby Portis","sal":19,"fppg":30.1,"pos":"C","team":"MIL","game":"MIL@BOS 1:00PM EDT","bench":false,"filter":"PF/C/F/UTIL","mins":31,"rk":1000,"val":1584.21,"id":"nba.p.5482$nba.g.2447590 - Bobby Portis"},{"name":"Pat Connaughton","sal":10,"fppg":19.5,"pos":"SG","team":"MIL","game":"MIL@BOS 1:00PM EDT","bench":false,"filter":"SG/G/UTIL","mins":23,"rk":89,"val":1950,"id":"nba.p.5501$nba.g.2447590 - Pat Connaughton"},{"name":"Grayson Allen","sal":14,"fppg":19.7,"pos":"SF","team":"MIL","game":"MIL@BOS 1:00PM EDT","bench":false,"filter":"SG/SF/F/G/UTIL","mins":26,"rk":130,"val":1407.14,"id":"nba.p.6032$nba.g.2447590 - Grayson Allen"},{"name":"Jevon Carter","sal":10,"fppg":9.7,"pos":"PG","team":"MIL","game":"MIL@BOS 1:00PM EDT","bench":false,"filter":"PG/G/UTIL","mins":19,"rk":448,"val":970,"id":"nba.p.6043$nba.g.2447590 - Jevon Carter"},{"name":"Lindell Wigginton","sal":10,"fppg":8.1,"pos":"PG","team":"MIL","game":"MIL@BOS 1:00PM EDT","bench":false,"filter":"PG/G/UTIL","mins":0,"rk":1000,"val":810,"id":"nba.p.6287$nba.g.2447590 - Lindell Wigginton"},{"name":"Rayjon Tucker","sal":10,"fppg":7.4,"pos":"SF","team":"MIL","game":"MIL@BOS 1:00PM EDT","bench":false,"filter":"SF/F/UTIL","mins":0,"rk":1000,"val":740,"id":"nba.p.6337$nba.g.2447590 - Rayjon Tucker"},{"name":"Jordan Nwora","sal":10,"fppg":14.1,"pos":"PF","team":"MIL","game":"MIL@BOS 1:00PM EDT","bench":false,"filter":"SF/PF/F/UTIL","mins":1,"rk":240,"val":1410,"id":"nba.p.6437$nba.g.2447590 - Jordan Nwora"},{"name":"Luca Vildoza","sal":10,"fppg":7.4,"pos":"PG","team":"MIL","game":"MIL@BOS 1:00PM EDT","bench":false,"filter":"PG/SG/G/UTIL","mins":3,"rk":1000,"val":740,"id":"nba.p.6509$nba.g.2447590 - Luca Vildoza"},{"name":"Sandro Mamukelashvili","sal":10,"fppg":7.9,"pos":"PF","team":"MIL","game":"MIL@BOS 1:00PM EDT","bench":false,"filter":"C/UTIL","mins":0,"rk":206,"val":790,"id":"nba.p.6596$nba.g.2447590 - Sandro Mamukelashvili"},{"name":"Al Horford","sal":22,"fppg":29.5,"pos":"PF","team":"BOS","game":"MIL@BOS 1:00PM EDT","bench":false,"filter":"PF/C/F/UTIL","mins":25,"rk":54,"val":1340.91,"id":"nba.p.4245$nba.g.2447590 - Al Horford"},{"name":"Marcus Smart","sal":20,"fppg":29.4,"pos":"PG","team":"BOS","game":"MIL@BOS 1:00PM EDT","bench":false,"filter":"PG/G/UTIL","mins":37,"rk":65,"val":1470,"id":"nba.p.5317$nba.g.2447590 - Marcus Smart"},{"name":"Nik Stauskas","sal":10,"fppg":3,"pos":"SF","team":"BOS","game":"MIL@BOS 1:00PM EDT","bench":false,"filter":"SG/G/UTIL","mins":0,"rk":1000,"val":300,"id":"nba.p.5319$nba.g.2447590 - Nik Stauskas"},{"name":"Jaylen Brown","sal":33,"fppg":37.7,"pos":"SG","team":"BOS","game":"MIL@BOS 1:00PM EDT","bench":false,"filter":"SG/SF/F/G/UTIL","mins":37,"rk":123,"val":1142.42,"id":"nba.p.5602$nba.g.2447590 - Jaylen Brown"},{"name":"Jayson Tatum","sal":44,"fppg":45.2,"pos":"SF","team":"BOS","game":"MIL@BOS 1:00PM EDT","bench":false,"filter":"SF/PF/F/UTIL","mins":37,"rk":18,"val":1027.27,"id":"nba.p.5765$nba.g.2447590 - Jayson Tatum"},{"name":"Derrick White","sal":16,"fppg":27.4,"pos":"SG","team":"BOS","game":"MIL@BOS 1:00PM EDT","bench":false,"filter":"PG/SG/G/UTIL","mins":22,"rk":28,"val":1712.5,"id":"nba.p.5842$nba.g.2447590 - Derrick White"},{"name":"Daniel Theis","sal":10,"fppg":17.8,"pos":"C","team":"BOS","game":"MIL@BOS 1:00PM EDT","bench":false,"filter":"C/UTIL","mins":9,"rk":223,"val":1780,"id":"nba.p.5880$nba.g.2447590 - Daniel Theis"},{"name":"Luke Kornet","sal":10,"fppg":6.6,"pos":"C","team":"BOS","game":"MIL@BOS 1:00PM EDT","bench":false,"filter":"C/UTIL","mins":0,"rk":1000,"val":660,"id":"nba.p.5903$nba.g.2447590 - Luke Kornet"},{"name":"Robert Williams","sal":22,"fppg":32.1,"pos":"C","team":"BOS","game":"MIL@BOS 1:00PM EDT","bench":false,"filter":"C/UTIL","mins":0,"rk":1000,"val":1459.09,"id":"nba.p.6038$nba.g.2447590 - Robert Williams"},{"name":"Grant Williams","sal":11,"fppg":16.8,"pos":"PF","team":"BOS","game":"MIL@BOS 1:00PM EDT","bench":false,"filter":"SF/PF/F/UTIL","mins":29,"rk":153,"val":1527.27,"id":"nba.p.6210$nba.g.2447590 - Grant Williams"},{"name":"Aaron Nesmith","sal":10,"fppg":7.3,"pos":"SF","team":"BOS","game":"MIL@BOS 1:00PM EDT","bench":false,"filter":"SG/SF/F/G/UTIL","mins":0,"rk":380,"val":730,"id":"nba.p.6406$nba.g.2447590 - Aaron Nesmith"},{"name":"Payton Pritchard","sal":10,"fppg":12,"pos":"PG","team":"BOS","game":"MIL@BOS 1:00PM EDT","bench":false,"filter":"PG/G/UTIL","mins":10,"rk":444,"val":1200,"id":"nba.p.6418$nba.g.2447590 - Payton Pritchard"},{"name":"Malik Fitts","sal":10,"fppg":3.1,"pos":"SF","team":"BOS","game":"MIL@BOS 1:00PM EDT","bench":false,"filter":"SF/F/UTIL","mins":0,"rk":478,"val":310,"id":"nba.p.6480$nba.g.2447590 - Malik Fitts"},{"name":"Brodric Thomas","sal":10,"fppg":4.1,"pos":"SG","team":"BOS","game":"MIL@BOS 1:00PM EDT","bench":false,"filter":"PG/G/UTIL","mins":0,"rk":1000,"val":410,"id":"nba.p.6483$nba.g.2447590 - Brodric Thomas"},{"name":"Sam Hauser","sal":10,"fppg":4.7,"pos":"PF","team":"BOS","game":"MIL@BOS 1:00PM EDT","bench":false,"filter":"PF/F/UTIL","mins":0,"rk":467,"val":470,"id":"nba.p.6619$nba.g.2447590 - Sam Hauser"},{"name":"Matt Ryan","sal":10,"fppg":6,"pos":"SG","team":"BOS","game":"MIL@BOS 1:00PM EDT","bench":false,"filter":"SF/F/UTIL","mins":0,"rk":1000,"val":600,"id":"nba.p.6654$nba.g.2447590 - Matt Ryan"},{"name":"Andre Iguodala","sal":10,"fppg":16.4,"pos":"SF","team":"GS","game":"GS@MEM 3:30PM EDT","bench":true,"filter":"SG/SF/F/G/UTIL","mins":0,"rk":200,"val":1640,"id":"nba.p.3826$nba.g.2447674 - Andre Iguodala"},{"name":"Stephen Curry","sal":38,"fppg":43,"pos":"PG","team":"GS","game":"GS@MEM 3:30PM EDT","bench":false,"filter":"PG/G/UTIL","mins":34,"rk":4,"val":1131.58,"id":"nba.p.4612$nba.g.2447674 - Stephen Curry"},{"name":"Nemanja Bjelica","sal":10,"fppg":15.7,"pos":"PF","team":"GS","game":"GS@MEM 3:30PM EDT","bench":false,"filter":"C/UTIL","mins":0,"rk":170,"val":1570,"id":"nba.p.4766$nba.g.2447674 - Nemanja Bjelica"},{"name":"Klay Thompson","sal":25,"fppg":31.4,"pos":"SG","team":"GS","game":"GS@MEM 3:30PM EDT","bench":false,"filter":"SG/SF/F/G/UTIL","mins":36,"rk":45,"val":1256,"id":"nba.p.4892$nba.g.2447674 - Klay Thompson"},{"name":"Draymond Green","sal":23,"fppg":31.5,"pos":"PF","team":"GS","game":"GS@MEM 3:30PM EDT","bench":false,"filter":"PF/C/F/UTIL","mins":33,"rk":26,"val":1369.57,"id":"nba.p.5069$nba.g.2447674 - Draymond Green"},{"name":"Otto Porter Jr.","sal":11,"fppg":20.7,"pos":"SF","team":"GS","game":"GS@MEM 3:30PM EDT","bench":false,"filter":"SF/PF/F/UTIL","mins":21,"rk":73,"val":1881.82,"id":"nba.p.5154$nba.g.2447674 - Otto Porter Jr."},{"name":"Andrew Wiggins","sal":22,"fppg":29.5,"pos":"SF","team":"GS","game":"GS@MEM 3:30PM EDT","bench":false,"filter":"SF/PF/F/UTIL","mins":32,"rk":46,"val":1340.91,"id":"nba.p.5292$nba.g.2447674 - Andrew Wiggins"},{"name":"Kevon Looney","sal":10,"fppg":19.9,"pos":"C","team":"GS","game":"GS@MEM 3:30PM EDT","bench":false,"filter":"C/UTIL","mins":14,"rk":133,"val":1990,"id":"nba.p.5490$nba.g.2447674 - Kevon Looney"},{"name":"Damion Lee","sal":10,"fppg":14,"pos":"PG","team":"GS","game":"GS@MEM 3:30PM EDT","bench":false,"filter":"PG/G/UTIL","mins":0,"rk":216,"val":1400,"id":"nba.p.5733$nba.g.2447674 - Damion Lee"},{"name":"Gary Payton II","sal":10,"fppg":17,"pos":"SG","team":"GS","game":"GS@MEM 3:30PM EDT","bench":false,"filter":"SG/G/UTIL","mins":16,"rk":191,"val":1700,"id":"nba.p.5739$nba.g.2447674 - Gary Payton II"},{"name":"Chris Chiozza","sal":10,"fppg":6.3,"pos":"PG","team":"GS","game":"GS@MEM 3:30PM EDT","bench":false,"filter":"PG/G/UTIL","mins":0,"rk":424,"val":630,"id":"nba.p.6119$nba.g.2447674 - Chris Chiozza"},{"name":"Jordan Poole","sal":35,"fppg":29.7,"pos":"PG","team":"GS","game":"GS@MEM 3:30PM EDT","bench":false,"filter":"PG/SG/G/UTIL","mins":31,"rk":53,"val":848.57,"id":"nba.p.6216$nba.g.2447674 - Jordan Poole"},{"name":"Quinndary Weatherspoon","sal":10,"fppg":5.2,"pos":"SG","team":"GS","game":"GS@MEM 3:30PM EDT","bench":false,"filter":"PG/G/UTIL","mins":0,"rk":1000,"val":520,"id":"nba.p.6237$nba.g.2447674 - Quinndary Weatherspoon"},{"name":"Juan Toscano-Anderson","sal":10,"fppg":11.3,"pos":"C","team":"GS","game":"GS@MEM 3:30PM EDT","bench":false,"filter":"C/UTIL","mins":0,"rk":327,"val":1130,"id":"nba.p.6329$nba.g.2447674 - Juan Toscano-Anderson"},{"name":"James Wiseman","sal":10,"fppg":21.5,"pos":"C","team":"GS","game":"GS@MEM 3:30PM EDT","bench":true,"filter":"C/UTIL","mins":0,"rk":1000,"val":2150,"id":"nba.p.6356$nba.g.2447674 - James Wiseman"},{"name":"Jonathan Kuminga","sal":10,"fppg":15.3,"pos":"PF","team":"GS","game":"GS@MEM 3:30PM EDT","bench":false,"filter":"PF/F/UTIL","mins":15,"rk":383,"val":1530,"id":"nba.p.6549$nba.g.2447674 - Jonathan Kuminga"},{"name":"Moses Moody","sal":10,"fppg":7.4,"pos":"SF","team":"GS","game":"GS@MEM 3:30PM EDT","bench":false,"filter":"SF/F/UTIL","mins":0,"rk":349,"val":740,"id":"nba.p.6556$nba.g.2447674 - Moses Moody"},{"name":"Steven Adams","sal":10,"fppg":26.6,"pos":"C","team":"MEM","game":"GS@MEM 3:30PM EDT","bench":true,"filter":"C/UTIL","mins":0,"rk":83,"val":2660,"id":"nba.p.5163$nba.g.2447674 - Steven Adams"},{"name":"Kyle Anderson","sal":11,"fppg":21.8,"pos":"PF","team":"MEM","game":"GS@MEM 3:30PM EDT","bench":false,"filter":"SF/PF/F/UTIL","mins":18,"rk":176,"val":1981.82,"id":"nba.p.5341$nba.g.2447674 - Kyle Anderson"},{"name":"Tyus Jones","sal":17,"fppg":20.4,"pos":"PG","team":"MEM","game":"GS@MEM 3:30PM EDT","bench":false,"filter":"PG/G/UTIL","mins":21,"rk":236,"val":1200,"id":"nba.p.5484$nba.g.2447674 - Tyus Jones"},{"name":"Dillon Brooks","sal":21,"fppg":28.1,"pos":"SF","team":"MEM","game":"GS@MEM 3:30PM EDT","bench":false,"filter":"SG/SF/F/G/UTIL","mins":32,"rk":56,"val":1338.1,"id":"nba.p.5858$nba.g.2447674 - Dillon Brooks"},{"name":"Jaren Jackson Jr.","sal":26,"fppg":32.6,"pos":"PF","team":"MEM","game":"GS@MEM 3:30PM EDT","bench":false,"filter":"PF/C/F/UTIL","mins":25,"rk":40,"val":1253.85,"id":"nba.p.6015$nba.g.2447674 - Jaren Jackson Jr."},{"name":"De'Anthony Melton","sal":10,"fppg":23.6,"pos":"SG","team":"MEM","game":"GS@MEM 3:30PM EDT","bench":false,"filter":"PG/SG/G/UTIL","mins":0,"rk":205,"val":2360,"id":"nba.p.6057$nba.g.2447674 - De'Anthony Melton"},{"name":"Ja Morant","sal":44,"fppg":46,"pos":"PG","team":"MEM","game":"GS@MEM 3:30PM EDT","bench":false,"filter":"PG/G/UTIL","mins":38,"rk":203,"val":1045.45,"id":"nba.p.6164$nba.g.2447674 - Ja Morant"},{"name":"Jarrett Culver","sal":10,"fppg":8,"pos":"SF","team":"MEM","game":"GS@MEM 3:30PM EDT","bench":false,"filter":"SG/SF/F/G/UTIL","mins":0,"rk":420,"val":800,"id":"nba.p.6168$nba.g.2447674 - Jarrett Culver"},{"name":"Brandon Clarke","sal":21,"fppg":24.3,"pos":"C","team":"MEM","game":"GS@MEM 3:30PM EDT","bench":false,"filter":"PF/C/F/UTIL","mins":31,"rk":237,"val":1157.14,"id":"nba.p.6209$nba.g.2447674 - Brandon Clarke"},{"name":"John Konchar","sal":10,"fppg":14.5,"pos":"SF","team":"MEM","game":"GS@MEM 3:30PM EDT","bench":false,"filter":"SG/SF/F/G/UTIL","mins":4,"rk":314,"val":1450,"id":"nba.p.6255$nba.g.2447674 - John Konchar"},{"name":"Desmond Bane","sal":28,"fppg":31.3,"pos":"SG","team":"MEM","game":"GS@MEM 3:30PM EDT","bench":false,"filter":"SG/G/UTIL","mins":37,"rk":93,"val":1117.86,"id":"nba.p.6422$nba.g.2447674 - Desmond Bane"},{"name":"Tyrell Terry","sal":10,"fppg":1,"pos":"SG","team":"MEM","game":"GS@MEM 3:30PM EDT","bench":false,"filter":"PG/SG/G/UTIL","mins":0,"rk":1000,"val":100,"id":"nba.p.6423$nba.g.2447674 - Tyrell Terry"},{"name":"Xavier Tillman","sal":10,"fppg":12.8,"pos":"C","team":"MEM","game":"GS@MEM 3:30PM EDT","bench":false,"filter":"C/UTIL","mins":0,"rk":177,"val":1280,"id":"nba.p.6427$nba.g.2447674 - Xavier Tillman"},{"name":"Killian Tillie","sal":10,"fppg":9,"pos":"C","team":"MEM","game":"GS@MEM 3:30PM EDT","bench":true,"filter":"PF/C/F/UTIL","mins":0,"rk":301,"val":900,"id":"nba.p.6460$nba.g.2447674 - Killian Tillie"},{"name":"Ziaire Williams","sal":10,"fppg":13.3,"pos":"SF","team":"MEM","game":"GS@MEM 3:30PM EDT","bench":true,"filter":"SF/F/UTIL","mins":9,"rk":348,"val":1330,"id":"nba.p.6552$nba.g.2447674 - Ziaire Williams"},{"name":"Santi Aldama","sal":10,"fppg":9.4,"pos":"PF","team":"MEM","game":"GS@MEM 3:30PM EDT","bench":true,"filter":"PF/C/F/UTIL","mins":0,"rk":376,"val":940,"id":"nba.p.6572$nba.g.2447674 - Santi Aldama"},{"name":"Yves Pons","sal":10,"fppg":3.6,"pos":"SF","team":"MEM","game":"GS@MEM 3:30PM EDT","bench":false,"filter":"SF/F/UTIL","mins":0,"rk":1000,"val":360,"id":"nba.p.6629$nba.g.2447674 - Yves Pons"}]}]