[{"sport":"PGA","league":"Draftkings","type":"Classic","about":"Mexico Open at Vidanta","games":[{"date":"04/28/2022","day":"Thursday","time":"05:45AM","zone":"EDT","filter":""}],"players":[{"name":"Jon Rahm","sal":11300,"fppg":81.44,"pos":"G","bench":false,"rk":2,"val":7.21,"id":"Jon Rahm (22311713)"},{"name":"Abraham Ancer","sal":10300,"fppg":66.85,"pos":"G","bench":false,"rk":20,"val":6.49,"id":"Abraham Ancer (22311715)"},{"name":"Tony Finau","sal":10400,"fppg":62.5,"pos":"G","bench":false,"rk":25,"val":6.01,"id":"Tony Finau (22311714)"},{"name":"Kevin Na","sal":10100,"fppg":61.12,"pos":"G","bench":false,"rk":32,"val":6.05,"id":"Kevin Na (22311716)"},{"name":"Patrick Reed","sal":10000,"fppg":64.9,"pos":"G","bench":false,"rk":33,"val":6.49,"id":"Patrick Reed (22311717)"},{"name":"Cameron Tringale","sal":9700,"fppg":68.63,"pos":"G","bench":false,"rk":49,"val":7.08,"id":"Cameron Tringale (22311720)"},{"name":"Matt Jones","sal":9000,"fppg":61.03,"pos":"G","bench":false,"rk":67,"val":6.78,"id":"Matt Jones (22311727)"},{"name":"Sebastian Munoz","sal":9800,"fppg":65.68,"pos":"G","bench":false,"rk":73,"val":6.7,"id":"Sebastian Munoz (22311719)"},{"name":"Anirban Lahiri","sal":7900,"fppg":51.94,"pos":"G","bench":false,"rk":85,"val":6.57,"id":"Anirban Lahiri (22311739)"},{"name":"Carlos Ortiz","sal":8600,"fppg":58.93,"pos":"G","bench":false,"rk":90,"val":6.85,"id":"Carlos Ortiz (22311731)"},{"name":"Chris Kirk","sal":9600,"fppg":65.21,"pos":"G","bench":false,"rk":92,"val":6.79,"id":"Chris Kirk (22311721)"},{"name":"Aaron Wise","sal":9500,"fppg":65.85,"pos":"G","bench":false,"rk":93,"val":6.93,"id":"Aaron Wise (22311722)"},{"name":"Gary Woodland","sal":9900,"fppg":58.27,"pos":"G","bench":false,"rk":96,"val":5.89,"id":"Gary Woodland (22311718)"},{"name":"Kevin Streelman","sal":9100,"fppg":56.16,"pos":"G","bench":false,"rk":98,"val":6.17,"id":"Kevin Streelman (22311726)"},{"name":"Cameron Champ","sal":9400,"fppg":48.78,"pos":"G","bench":false,"rk":104,"val":5.19,"id":"Cameron Champ (22311723)"},{"name":"Lanto Griffin","sal":8300,"fppg":62.63,"pos":"G","bench":false,"rk":107,"val":7.55,"id":"Lanto Griffin (22311734)"},{"name":"Chad Ramey","sal":7900,"fppg":59.94,"pos":"G","bench":false,"rk":119,"val":7.59,"id":"Chad Ramey (22311738)"},{"name":"Aaron Rai","sal":8700,"fppg":56.72,"pos":"G","bench":false,"rk":122,"val":6.52,"id":"Aaron Rai (22311730)"},{"name":"Sahith Theegala","sal":8800,"fppg":64.39,"pos":"G","bench":false,"rk":125,"val":7.32,"id":"Sahith Theegala (22311729)"},{"name":"Rafa Cabrera Bello","sal":7400,"fppg":55.7,"pos":"G","bench":false,"rk":126,"val":7.53,"id":"Rafa Cabrera Bello (22311751)"},{"name":"Matt Wallace","sal":7000,"fppg":41.25,"pos":"G","bench":false,"rk":134,"val":5.89,"id":"Matt Wallace (22311771)"},{"name":"C.T. Pan","sal":8100,"fppg":62.83,"pos":"G","bench":false,"rk":136,"val":7.76,"id":"C.T. Pan (22311736)"},{"name":"Emiliano Grillo","sal":7200,"fppg":47.22,"pos":"G","bench":false,"rk":138,"val":6.56,"id":"Emiliano Grillo (22311756)"},{"name":"Kramer Hickok","sal":7200,"fppg":50.56,"pos":"G","bench":false,"rk":143,"val":7.02,"id":"Kramer Hickok (22311760)"},{"name":"Robert Streb","sal":7000,"fppg":51.34,"pos":"G","bench":false,"rk":148,"val":7.33,"id":"Robert Streb (22311772)"},{"name":"Andrew Putnam","sal":7000,"fppg":56.06,"pos":"G","bench":false,"rk":151,"val":8.01,"id":"Andrew Putnam (22311769)"},{"name":"Brendon Todd","sal":9300,"fppg":56.77,"pos":"G","bench":false,"rk":156,"val":6.1,"id":"Brendon Todd (22311724)"},{"name":"Taylor Moore","sal":8200,"fppg":51.46,"pos":"G","bench":false,"rk":160,"val":6.28,"id":"Taylor Moore (22311735)"},{"name":"J.T. Poston","sal":7500,"fppg":46.38,"pos":"G","bench":false,"rk":168,"val":6.18,"id":"J.T. Poston (22311746)"},{"name":"Adam Svensson","sal":7300,"fppg":54.94,"pos":"G","bench":false,"rk":176,"val":7.53,"id":"Adam Svensson (22311753)"},{"name":"Adam Long","sal":7800,"fppg":58.29,"pos":"G","bench":false,"rk":177,"val":7.47,"id":"Adam Long (22311740)"},{"name":"Greyson Sigg","sal":7300,"fppg":61.22,"pos":"G","bench":false,"rk":181,"val":8.39,"id":"Greyson Sigg (22311754)"},{"name":"Russell Knox","sal":9200,"fppg":61.82,"pos":"G","bench":false,"rk":183,"val":6.72,"id":"Russell Knox (22311725)"},{"name":"Doug Ghim","sal":8900,"fppg":55.7,"pos":"G","bench":false,"rk":184,"val":6.26,"id":"Doug Ghim (22311728)"},{"name":"Davis Riley","sal":8500,"fppg":59.06,"pos":"G","bench":false,"rk":185,"val":6.95,"id":"Davis Riley (22311732)"},{"name":"Charles Howell III","sal":8400,"fppg":58.96,"pos":"G","bench":false,"rk":189,"val":7.02,"id":"Charles Howell III (22311733)"},{"name":"Pat Perez","sal":7500,"fppg":51.7,"pos":"G","bench":false,"rk":190,"val":6.89,"id":"Pat Perez (22311747)"},{"name":"Adam Schenk","sal":6900,"fppg":45.19,"pos":"G","bench":false,"rk":191,"val":6.55,"id":"Adam Schenk (22311776)"},{"name":"Scott Stallings","sal":7700,"fppg":55.79,"pos":"G","bench":false,"rk":195,"val":7.25,"id":"Scott Stallings (22311742)"},{"name":"Stephan Jaeger","sal":6500,"fppg":42.76,"pos":"G","bench":false,"rk":197,"val":6.58,"id":"Stephan Jaeger (22311806)"},{"name":"Michael Thompson","sal":7200,"fppg":58.1,"pos":"G","bench":false,"rk":202,"val":8.07,"id":"Michael Thompson (22311759)"},{"name":"David Lipsky","sal":7700,"fppg":50.69,"pos":"G","bench":false,"rk":204,"val":6.58,"id":"David Lipsky (22311743)"},{"name":"Alex Smalley","sal":7400,"fppg":57.03,"pos":"G","bench":false,"rk":205,"val":7.71,"id":"Alex Smalley (22311750)"},{"name":"Kurt Kitayama","sal":7100,"fppg":48.08,"pos":"G","bench":false,"rk":208,"val":6.77,"id":"Kurt Kitayama (22311762)"},{"name":"Lee Hodges","sal":6900,"fppg":53.19,"pos":"G","bench":false,"rk":216,"val":7.71,"id":"Lee Hodges (22311778)"},{"name":"Hayden Buckley","sal":6800,"fppg":53.94,"pos":"G","bench":false,"rk":227,"val":7.93,"id":"Hayden Buckley (22311781)"},{"name":"Chez Reavie","sal":6800,"fppg":47.12,"pos":"G","bench":false,"rk":232,"val":6.93,"id":"Chez Reavie (22311786)"},{"name":"Joseph Bramlett","sal":7100,"fppg":51.26,"pos":"G","bench":false,"rk":234,"val":7.22,"id":"Joseph Bramlett (22311766)"},{"name":"Kiradech Aphibarnrat","sal":6900,"fppg":48.96,"pos":"G","bench":false,"rk":237,"val":7.1,"id":"Kiradech Aphibarnrat (22311773)"},{"name":"Max McGreevy","sal":6400,"fppg":48.75,"pos":"G","bench":false,"rk":240,"val":7.62,"id":"Max McGreevy (22311812)"},{"name":"Brian Stuard","sal":7300,"fppg":50.32,"pos":"G","bench":false,"rk":241,"val":6.89,"id":"Brian Stuard (22311755)"},{"name":"Nick Taylor","sal":7100,"fppg":56.25,"pos":"G","bench":false,"rk":256,"val":7.92,"id":"Nick Taylor (22311763)"},{"name":"Patrick Rodgers","sal":7600,"fppg":52.37,"pos":"G","bench":false,"rk":265,"val":6.89,"id":"Patrick Rodgers (22311744)"},{"name":"Kevin Tway","sal":6500,"fppg":45.68,"pos":"G","bench":false,"rk":269,"val":7.03,"id":"Kevin Tway (22311804)"},{"name":"Peter Malnati","sal":6900,"fppg":56.08,"pos":"G","bench":false,"rk":273,"val":8.13,"id":"Peter Malnati (22311775)"},{"name":"Mark Hubbard","sal":8000,"fppg":72.12,"pos":"G","bench":false,"rk":274,"val":9.02,"id":"Mark Hubbard (22311737)"},{"name":"Scott Piercy","sal":7200,"fppg":49,"pos":"G","bench":false,"rk":275,"val":6.81,"id":"Scott Piercy (22311758)"},{"name":"Hank Lebioda","sal":6700,"fppg":42.38,"pos":"G","bench":false,"rk":277,"val":6.33,"id":"Hank Lebioda (22311787)"},{"name":"Wyndham Clark","sal":7600,"fppg":55.88,"pos":"G","bench":false,"rk":279,"val":7.35,"id":"Wyndham Clark (22311745)"},{"name":"Danny Lee","sal":7100,"fppg":52,"pos":"G","bench":false,"rk":281,"val":7.32,"id":"Danny Lee (22311764)"},{"name":"John Huh","sal":7000,"fppg":56.96,"pos":"G","bench":false,"rk":282,"val":8.14,"id":"John Huh (22311770)"},{"name":"Roger Sloan","sal":6600,"fppg":45.53,"pos":"G","bench":false,"rk":284,"val":6.9,"id":"Roger Sloan (22311799)"},{"name":"Brandon Hagy","sal":6400,"fppg":42.19,"pos":"G","bench":false,"rk":294,"val":6.59,"id":"Brandon Hagy (22311811)"},{"name":"Peter Uihlein","sal":7000,"fppg":60.54,"pos":"G","bench":false,"rk":299,"val":8.65,"id":"Peter Uihlein (22311768)"},{"name":"Satoshi Kodaira","sal":6500,"fppg":53.21,"pos":"G","bench":false,"rk":300,"val":8.19,"id":"Satoshi Kodaira (22311805)"},{"name":"Richy Werenski","sal":6400,"fppg":42.43,"pos":"G","bench":false,"rk":301,"val":6.63,"id":"Richy Werenski (22311814)"},{"name":"Nate Lashley","sal":7500,"fppg":57.47,"pos":"G","bench":false,"rk":308,"val":7.66,"id":"Nate Lashley (22311748)"},{"name":"Austin Smotherman","sal":7800,"fppg":53.25,"pos":"G","bench":false,"rk":312,"val":6.83,"id":"Austin Smotherman (22311741)"},{"name":"Brice Garnett","sal":6700,"fppg":46.76,"pos":"G","bench":false,"rk":316,"val":6.98,"id":"Brice Garnett (22311790)"},{"name":"Trey Mullinax","sal":6800,"fppg":47.73,"pos":"G","bench":false,"rk":317,"val":7.02,"id":"Trey Mullinax (22311785)"},{"name":"David Skinns","sal":6300,"fppg":45.42,"pos":"G","bench":false,"rk":324,"val":7.21,"id":"David Skinns (22311822)"},{"name":"James Hahn","sal":6800,"fppg":40.58,"pos":"G","bench":false,"rk":327,"val":5.97,"id":"James Hahn (22311784)"},{"name":"Ryan Armour","sal":6900,"fppg":50.39,"pos":"G","bench":false,"rk":329,"val":7.3,"id":"Ryan Armour (22311777)"},{"name":"Ben Martin","sal":6900,"fppg":52.5,"pos":"G","bench":false,"rk":337,"val":7.61,"id":"Ben Martin (22311774)"},{"name":"Brandon Wu","sal":7300,"fppg":47.89,"pos":"G","bench":false,"rk":339,"val":6.56,"id":"Brandon Wu (22311752)"},{"name":"Paul Barjon","sal":6500,"fppg":46.85,"pos":"G","bench":false,"rk":349,"val":7.21,"id":"Paul Barjon (22311807)"},{"name":"Andrew Novak","sal":6700,"fppg":50.89,"pos":"G","bench":false,"rk":361,"val":7.6,"id":"Andrew Novak (22311789)"},{"name":"Joshua Creel","sal":6400,"fppg":37.77,"pos":"G","bench":false,"rk":370,"val":5.9,"id":"Joshua Creel (22311817)"},{"name":"Graeme McDowell","sal":7100,"fppg":48.54,"pos":"G","bench":false,"rk":374,"val":6.84,"id":"Graeme McDowell (22311761)"},{"name":"Seth Reeves","sal":6400,"fppg":47.75,"pos":"G","bench":false,"rk":385,"val":7.46,"id":"Seth Reeves (22311810)"},{"name":"Dylan Wu","sal":6600,"fppg":51.54,"pos":"G","bench":false,"rk":392,"val":7.81,"id":"Dylan Wu (22311795)"},{"name":"Vaughn Taylor","sal":6900,"fppg":56.17,"pos":"G","bench":false,"rk":393,"val":8.14,"id":"Vaughn Taylor (22311779)"},{"name":"Chase Seiffert","sal":7100,"fppg":61.43,"pos":"G","bench":false,"rk":398,"val":8.65,"id":"Chase Seiffert (22311765)"},{"name":"Bo Hoag","sal":6600,"fppg":52.35,"pos":"G","bench":false,"rk":403,"val":7.93,"id":"Bo Hoag (22311794)"},{"name":"Camilo Villegas","sal":6600,"fppg":49.25,"pos":"G","bench":false,"rk":413,"val":7.46,"id":"Camilo Villegas (22311796)"},{"name":"Callum Tarren","sal":6700,"fppg":49.96,"pos":"G","bench":false,"rk":415,"val":7.46,"id":"Callum Tarren (22311788)"},{"name":"Bo Van Pelt","sal":6200,"fppg":34.62,"pos":"G","bench":false,"rk":433,"val":5.58,"id":"Bo Van Pelt (22311829)"},{"name":"Curtis Thompson","sal":6700,"fppg":48.5,"pos":"G","bench":false,"rk":440,"val":7.24,"id":"Curtis Thompson (22311793)"},{"name":"Justin Lower","sal":6800,"fppg":55.85,"pos":"G","bench":false,"rk":441,"val":8.21,"id":"Justin Lower (22311783)"},{"name":"Austin Cook","sal":6500,"fppg":44.23,"pos":"G","bench":false,"rk":442,"val":6.8,"id":"Austin Cook (22311808)"},{"name":"Nick Hardy","sal":7000,"fppg":47.5,"pos":"G","bench":false,"rk":465,"val":6.79,"id":"Nick Hardy (22311767)"},{"name":"Martin Trainer","sal":6300,"fppg":41.47,"pos":"G","bench":false,"rk":478,"val":6.58,"id":"Martin Trainer (22311826)"},{"name":"Kevin Chappell","sal":7400,"fppg":54.18,"pos":"G","bench":false,"rk":491,"val":7.32,"id":"Kevin Chappell (22311749)"},{"name":"Ben Kohles","sal":6500,"fppg":54.42,"pos":"G","bench":false,"rk":497,"val":8.37,"id":"Ben Kohles (22311803)"},{"name":"Jared Wolfe","sal":6200,"fppg":45.11,"pos":"G","bench":false,"rk":502,"val":7.28,"id":"Jared Wolfe (22311834)"},{"name":"Luke Donald","sal":6800,"fppg":51.75,"pos":"G","bench":false,"rk":519,"val":7.61,"id":"Luke Donald (22311782)"},{"name":"Wesley Bryan","sal":6600,"fppg":49.56,"pos":"G","bench":false,"rk":524,"val":7.51,"id":"Wesley Bryan (22311800)"},{"name":"Jason Dufner","sal":6400,"fppg":40.89,"pos":"G","bench":false,"rk":525,"val":6.39,"id":"Jason Dufner (22311813)"},{"name":"Michael Gligic","sal":6400,"fppg":46.29,"pos":"G","bench":false,"rk":528,"val":7.23,"id":"Michael Gligic (22311818)"},{"name":"Brett Drewitt","sal":6200,"fppg":49.34,"pos":"G","bench":false,"rk":532,"val":7.96,"id":"Brett Drewitt (22311833)"},{"name":"Tommy Gainey","sal":6300,"fppg":40.89,"pos":"G","bench":false,"rk":556,"val":6.49,"id":"Tommy Gainey (22311819)"},{"name":"Bill Haas","sal":6700,"fppg":52.22,"pos":"G","bench":false,"rk":567,"val":7.79,"id":"Bill Haas (22311792)"},{"name":"Jonathan Byrd","sal":6200,"fppg":51.7,"pos":"G","bench":false,"rk":569,"val":8.34,"id":"Jonathan Byrd (22311831)"},{"name":"Scott Brown","sal":6400,"fppg":57.11,"pos":"G","bench":false,"rk":612,"val":8.92,"id":"Scott Brown (22311816)"},{"name":"Roberto Diaz","sal":6200,"fppg":50.56,"pos":"G","bench":false,"rk":624,"val":8.15,"id":"Roberto Diaz (22311832)"},{"name":"David Lingmerth","sal":6200,"fppg":50.75,"pos":"G","bench":false,"rk":633,"val":8.19,"id":"David Lingmerth (22311830)"},{"name":"Scott Gutschewski","sal":6500,"fppg":50.41,"pos":"G","bench":false,"rk":635,"val":7.76,"id":"Scott Gutschewski (22311809)"},{"name":"Patrick Flavin","sal":6500,"fppg":75,"pos":"G","bench":false,"rk":646,"val":11.54,"id":"Patrick Flavin (22311802)"},{"name":"Ryan Blaum","sal":6300,"fppg":61.8,"pos":"G","bench":false,"rk":676,"val":9.81,"id":"Ryan Blaum (22311820)"},{"name":"Bryson Nimmer","sal":6300,"fppg":52.38,"pos":"G","bench":false,"rk":688,"val":8.31,"id":"Bryson Nimmer (22311821)"},{"name":"Aaron Baddeley","sal":6700,"fppg":59.88,"pos":"G","bench":false,"rk":688,"val":8.94,"id":"Aaron Baddeley (22311791)"},{"name":"Kelly Kraft","sal":6000,"fppg":37.07,"pos":"G","bench":false,"rk":719,"val":6.18,"id":"Kelly Kraft (22311848)"},{"name":"Fabian Gomez","sal":6400,"fppg":47.18,"pos":"G","bench":false,"rk":726,"val":7.37,"id":"Fabian Gomez (22311815)"},{"name":"Turk Pettit","sal":6300,"fppg":34.62,"pos":"G","bench":false,"rk":766,"val":5.5,"id":"Turk Pettit (22311827)"},{"name":"Jim Knous","sal":6100,"fppg":53.3,"pos":"G","bench":false,"rk":787,"val":8.74,"id":"Jim Knous (22311843)"},{"name":"Grayson Murray","sal":6100,"fppg":49.43,"pos":"G","bench":false,"rk":813,"val":8.1,"id":"Grayson Murray (22311839)"},{"name":"David Hearn","sal":6300,"fppg":46.55,"pos":"G","bench":false,"rk":867,"val":7.39,"id":"David Hearn (22311824)"},{"name":"Mark Hensby","sal":6100,"fppg":54.67,"pos":"G","bench":false,"rk":975,"val":8.96,"id":"Mark Hensby (22311841)"},{"name":"Robert Garrigus","sal":6600,"fppg":70,"pos":"G","bench":false,"rk":1053,"val":10.61,"id":"Robert Garrigus (22311801)"},{"name":"Isidro Benitez","sal":6000,"fppg":0,"pos":"G","bench":false,"rk":1256,"val":0,"id":"Isidro Benitez (22311852)"},{"name":"Ricky Barnes","sal":6100,"fppg":37.88,"pos":"G","bench":false,"rk":1262,"val":6.21,"id":"Ricky Barnes (22311838)"},{"name":"Jonas Blixt","sal":6100,"fppg":32.8,"pos":"G","bench":false,"rk":1337,"val":5.38,"id":"Jonas Blixt (22311845)"},{"name":"Armando Favela","sal":6200,"fppg":0,"pos":"G","bench":false,"rk":1383,"val":0,"id":"Armando Favela (22311828)"},{"name":"D.J. Trahan","sal":6200,"fppg":46.3,"pos":"G","bench":false,"rk":1411,"val":7.47,"id":"D.J. Trahan (22311836)"},{"name":"Greg Chalmers","sal":6100,"fppg":53.12,"pos":"G","bench":false,"rk":1442,"val":8.71,"id":"Greg Chalmers (22311842)"},{"name":"Johnson Wagner","sal":6200,"fppg":67.75,"pos":"G","bench":false,"rk":1468,"val":10.93,"id":"Johnson Wagner (22311835)"},{"name":"Derek Ernst","sal":6000,"fppg":48.5,"pos":"G","bench":false,"rk":1545,"val":8.08,"id":"Derek Ernst (22332619)"},{"name":"Arjun Atwal","sal":6100,"fppg":52,"pos":"G","bench":false,"rk":1679,"val":8.52,"id":"Arjun Atwal (22311844)"},{"name":"Matt Every","sal":6000,"fppg":34.25,"pos":"G","bench":false,"rk":1715,"val":5.71,"id":"Matt Every (22311851)"},{"name":"Santiago De la Fuente","sal":6000,"fppg":0,"pos":"G","bench":false,"rk":1724,"val":0,"id":"Santiago De la Fuente (22311855)"},{"name":"Jose Antonio Safa","sal":6000,"fppg":0,"pos":"G","bench":false,"rk":1724,"val":0,"id":"Jose Antonio Safa (22311853)"},{"name":"Ben Willman","sal":6000,"fppg":0,"pos":"G","bench":false,"rk":1724,"val":0,"id":"Ben Willman (22311850)"},{"name":"Jeffrey Kang","sal":6100,"fppg":24.5,"pos":"G","bench":false,"rk":1724,"val":4.02,"id":"Jeffrey Kang (22311840)"},{"name":"Ben Crane","sal":6100,"fppg":34,"pos":"G","bench":false,"rk":1724,"val":5.57,"id":"Ben Crane (22311846)"},{"name":"D.A. Points","sal":6000,"fppg":53,"pos":"G","bench":false,"rk":1724,"val":8.83,"id":"D.A. Points (22311849)"},{"name":"Manuel Inman","sal":6000,"fppg":0,"pos":"G","bench":false,"rk":2000,"val":0,"id":"Manuel Inman (22311856)"},{"name":"Jose Cristobal  Islas","sal":6000,"fppg":0,"pos":"G","bench":false,"rk":2000,"val":0,"id":"Jose Cristobal  Islas (22311854)"},{"name":"Richard S Johnson","sal":6100,"fppg":29.88,"pos":"G","bench":false,"rk":2000,"val":4.9,"id":"Richard S Johnson (22332618)"},{"name":"Dawie Van der Walt","sal":6100,"fppg":37.25,"pos":"G","bench":false,"rk":2000,"val":6.11,"id":"Dawie Van der Walt (22311837)"},{"name":"Alvaro Ortiz","sal":6300,"fppg":41.92,"pos":"G","bench":false,"rk":2000,"val":6.65,"id":"Alvaro Ortiz (22311825)"},{"name":"Sung Kang","sal":6600,"fppg":50.16,"pos":"G","bench":false,"rk":2000,"val":7.6,"id":"Sung Kang (22311797)"},{"name":"Seung-Yul Noh","sal":6300,"fppg":49.38,"pos":"G","bench":false,"rk":2000,"val":7.84,"id":"Seung-Yul Noh (22311823)"},{"name":"Tyler Duncan","sal":7200,"fppg":58.57,"pos":"G","bench":false,"rk":2000,"val":8.13,"id":"Tyler Duncan (22311757)"},{"name":"Sang-Moon Bae","sal":6000,"fppg":50.23,"pos":"G","bench":false,"rk":2000,"val":8.37,"id":"Sang-Moon Bae (22311847)"},{"name":"Vince Whaley","sal":6800,"fppg":59.19,"pos":"G","bench":false,"rk":2000,"val":8.7,"id":"Vince Whaley (22311780)"},{"name":"Ben Griffin","sal":6600,"fppg":76.88,"pos":"G","bench":false,"rk":2000,"val":11.65,"id":"Ben Griffin (22311798)"}]},{"sport":"PGA","league":"FanDuel","type":"Classic","about":"Mexico Open at Vidanta","games":[{"date":"04/28/2022","day":"Thursday","time":"05:45AM","zone":"EDT","filter":""}],"players":[{"Player ID + Player Name":"75241-78707:Jon Rahm","Id":"75241-78707","":"","Roster Position":"G","name":"Jon Rahm","sal":12200,"fppg":85.17,"pos":"G","bench":false,"rk":2,"val":6.98},{"Player ID + Player Name":"75241-77806:Abraham Ancer","Id":"75241-77806","":"","Roster Position":"G","name":"Abraham Ancer","sal":11700,"fppg":66.94,"pos":"G","bench":false,"rk":20,"val":5.72},{"Player ID + Player Name":"75241-78078:Tony Finau","Id":"75241-78078","":"","Roster Position":"G","name":"Tony Finau","sal":11500,"fppg":63.28,"pos":"G","bench":false,"rk":25,"val":5.5},{"Player ID + Player Name":"75241-78722:Patrick Reed","Id":"75241-78722","":"","Roster Position":"G","name":"Patrick Reed","sal":11400,"fppg":63.6,"pos":"G","bench":false,"rk":33,"val":5.58},{"Player ID + Player Name":"75241-78998:Gary Woodland","Id":"75241-78998","":"","Roster Position":"G","name":"Gary Woodland","sal":11300,"fppg":57.4,"pos":"G","bench":false,"rk":96,"val":5.08},{"Player ID + Player Name":"75241-78588:Kevin Na","Id":"75241-78588","":"","Roster Position":"G","name":"Kevin Na","sal":11200,"fppg":63.99,"pos":"G","bench":false,"rk":32,"val":5.71},{"Player ID + Player Name":"75241-78579:Sebastian Munoz","Id":"75241-78579","":"","Roster Position":"G","name":"Sebastian Munoz","sal":11000,"fppg":62.18,"pos":"G","bench":false,"rk":73,"val":5.65},{"Player ID + Player Name":"75241-78913:Cameron Tringale","Id":"75241-78913","":"","Roster Position":"G","name":"Cameron Tringale","sal":10900,"fppg":69.81,"pos":"G","bench":false,"rk":49,"val":6.4},{"Player ID + Player Name":"75241-78355:Chris Kirk","Id":"75241-78355","":"","Roster Position":"G","name":"Chris Kirk","sal":10800,"fppg":67.15,"pos":"G","bench":false,"rk":92,"val":6.22},{"Player ID + Player Name":"75241-78992:Aaron Wise","Id":"75241-78992","":"","Roster Position":"G","name":"Aaron Wise","sal":10700,"fppg":66.88,"pos":"G","bench":false,"rk":93,"val":6.25},{"Player ID + Player Name":"75241-78857:Kevin Streelman","Id":"75241-78857","":"","Roster Position":"G","name":"Kevin Streelman","sal":10600,"fppg":56.61,"pos":"G","bench":false,"rk":98,"val":5.34},{"Player ID + Player Name":"75241-78709:Aaron Rai","Id":"75241-78709","":"","Roster Position":"G","name":"Aaron Rai","sal":10500,"fppg":57.51,"pos":"G","bench":false,"rk":122,"val":5.48},{"Player ID + Player Name":"75241-80553:Cameron Champ","Id":"75241-80553","":"","Roster Position":"G","name":"Cameron Champ","sal":10400,"fppg":44.87,"pos":"G","bench":false,"rk":104,"val":4.31},{"Player ID + Player Name":"75241-78363:Russell Knox","Id":"75241-78363","":"","Roster Position":"G","name":"Russell Knox","sal":10300,"fppg":63.75,"pos":"G","bench":false,"rk":183,"val":6.19},{"Player ID + Player Name":"75241-78904:Brendon Todd","Id":"75241-78904","":"","Roster Position":"G","name":"Brendon Todd","sal":10200,"fppg":57.84,"pos":"G","bench":false,"rk":156,"val":5.67},{"Player ID + Player Name":"75241-82444:Doug Ghim","Id":"75241-82444","":"","Roster Position":"G","name":"Doug Ghim","sal":10100,"fppg":54.8,"pos":"G","bench":false,"rk":184,"val":5.43},{"Player ID + Player Name":"75241-78626:Carlos Ortiz","Id":"75241-78626","":"","Roster Position":"G","name":"Carlos Ortiz","sal":10000,"fppg":55.99,"pos":"G","bench":false,"rk":90,"val":5.6},{"Player ID + Player Name":"75241-82773:C.T. Pan","Id":"75241-82773","":"","Roster Position":"G","name":"C.T. Pan","sal":9900,"fppg":60.46,"pos":"G","bench":false,"rk":136,"val":6.11},{"Player ID + Player Name":"75241-78295:Matt Jones","Id":"75241-78295","":"","Roster Position":"G","name":"Matt Jones","sal":9900,"fppg":62.73,"pos":"G","bench":false,"rk":67,"val":6.34},{"Player ID + Player Name":"75241-79759:Sahith Theegala","Id":"75241-79759","":"","Roster Position":"G","name":"Sahith Theegala","sal":9800,"fppg":65.04,"pos":"G","bench":false,"rk":125,"val":6.64},{"Player ID + Player Name":"75241-79599:Davis Riley","Id":"75241-79599","":"","Roster Position":"G","name":"Davis Riley","sal":9800,"fppg":58.82,"pos":"G","bench":false,"rk":185,"val":6},{"Player ID + Player Name":"75241-79480:Lanto Griffin","Id":"75241-79480","":"","Roster Position":"G","name":"Lanto Griffin","sal":9700,"fppg":64.28,"pos":"G","bench":false,"rk":107,"val":6.63},{"Player ID + Player Name":"75241-78239:Charles Howell III","Id":"75241-78239","":"","Roster Position":"G","name":"Charles Howell III","sal":9700,"fppg":61.4,"pos":"G","bench":false,"rk":189,"val":6.33},{"Player ID + Player Name":"75241-78739:Patrick Rodgers","Id":"75241-78739","":"","Roster Position":"G","name":"Patrick Rodgers","sal":9600,"fppg":51.53,"pos":"G","bench":false,"rk":265,"val":5.37},{"Player ID + Player Name":"75241-78241:Mark Hubbard","Id":"75241-78241","":"","Roster Position":"G","name":"Mark Hubbard","sal":9600,"fppg":61.21,"pos":"G","bench":false,"rk":274,"val":6.38},{"Player ID + Player Name":"75241-78450:David Lipsky","Id":"75241-78450","":"","Roster Position":"G","name":"David Lipsky","sal":9500,"fppg":49.92,"pos":"G","bench":false,"rk":204,"val":5.26},{"Player ID + Player Name":"75241-78566:Taylor Moore","Id":"75241-78566","":"","Roster Position":"G","name":"Taylor Moore","sal":9500,"fppg":50.95,"pos":"G","bench":false,"rk":160,"val":5.36},{"Player ID + Player Name":"75241-80788:Wyndham Clark","Id":"75241-80788","":"","Roster Position":"G","name":"Wyndham Clark","sal":9400,"fppg":56.41,"pos":"G","bench":false,"rk":279,"val":6},{"Player ID + Player Name":"75241-78839:Scott Stallings","Id":"75241-78839","":"","Roster Position":"G","name":"Scott Stallings","sal":9400,"fppg":57.94,"pos":"G","bench":false,"rk":195,"val":6.16},{"Player ID + Player Name":"75241-80362:Austin Smotherman","Id":"75241-80362","":"","Roster Position":"G","name":"Austin Smotherman","sal":9300,"fppg":52.65,"pos":"G","bench":false,"rk":312,"val":5.66},{"Player ID + Player Name":"75241-79597:Chad Ramey","Id":"75241-79597","":"","Roster Position":"G","name":"Chad Ramey","sal":9300,"fppg":59.81,"pos":"G","bench":false,"rk":119,"val":6.43},{"Player ID + Player Name":"75241-78389:Anirban Lahiri","Id":"75241-78389","":"","Roster Position":"G","name":"Anirban Lahiri","sal":9200,"fppg":50.69,"pos":"G","bench":false,"rk":85,"val":5.51},{"Player ID + Player Name":"75241-78403:Nate Lashley","Id":"75241-78403","":"","Roster Position":"G","name":"Nate Lashley","sal":9200,"fppg":59.46,"pos":"G","bench":false,"rk":308,"val":6.46},{"Player ID + Player Name":"75241-79454:Tyler Duncan","Id":"75241-79454","":"","Roster Position":"G","name":"Tyler Duncan","sal":9100,"fppg":59.01,"pos":"G","bench":false,"rk":2000,"val":6.48},{"Player ID + Player Name":"75241-78689:J.T. Poston","Id":"75241-78689","":"","Roster Position":"G","name":"J.T. Poston","sal":9100,"fppg":44.54,"pos":"G","bench":false,"rk":168,"val":4.89},{"Player ID + Player Name":"75241-77934:Kevin Chappell","Id":"75241-77934","":"","Roster Position":"G","name":"Kevin Chappell","sal":9000,"fppg":54.59,"pos":"G","bench":true,"rk":491,"val":6.07},{"Player ID + Player Name":"75241-78456:Adam Long","Id":"75241-78456","":"","Roster Position":"G","name":"Adam Long","sal":9000,"fppg":58.83,"pos":"G","bench":false,"rk":177,"val":6.54},{"Player ID + Player Name":"75241-77810:Kiradech Aphibarnrat","Id":"75241-77810","":"","Roster Position":"G","name":"Kiradech Aphibarnrat","sal":9000,"fppg":50.94,"pos":"G","bench":false,"rk":237,"val":5.66},{"Player ID + Player Name":"75241-78665:Pat Perez","Id":"75241-78665","":"","Roster Position":"G","name":"Pat Perez","sal":8900,"fppg":51.94,"pos":"G","bench":false,"rk":190,"val":5.84},{"Player ID + Player Name":"75241-78675:Scott Piercy","Id":"75241-78675","":"","Roster Position":"G","name":"Scott Piercy","sal":8900,"fppg":48.28,"pos":"G","bench":false,"rk":275,"val":5.42},{"Player ID + Player Name":"75241-77908:Rafa Cabrera Bello","Id":"75241-77908","":"","Roster Position":"G","name":"Rafa Cabrera Bello","sal":8900,"fppg":45.65,"pos":"G","bench":false,"rk":126,"val":5.13},{"Player ID + Player Name":"75241-78862:Brian Stuard","Id":"75241-78862","":"","Roster Position":"G","name":"Brian Stuard","sal":8800,"fppg":49.87,"pos":"G","bench":false,"rk":241,"val":5.67},{"Player ID + Player Name":"75241-78872:Adam Svensson","Id":"75241-78872","":"","Roster Position":"G","name":"Adam Svensson","sal":8800,"fppg":55.44,"pos":"G","bench":false,"rk":176,"val":6.3},{"Player ID + Player Name":"75241-78214:Kramer Hickok","Id":"75241-78214","":"","Roster Position":"G","name":"Kramer Hickok","sal":8800,"fppg":50.68,"pos":"G","bench":false,"rk":143,"val":5.76},{"Player ID + Player Name":"75241-78415:Danny Lee","Id":"75241-78415","":"","Roster Position":"G","name":"Danny Lee","sal":8700,"fppg":50.62,"pos":"G","bench":false,"rk":281,"val":5.82},{"Player ID + Player Name":"75241-107350:Brandon Wu","Id":"75241-107350","":"","Roster Position":"G","name":"Brandon Wu","sal":8700,"fppg":49.02,"pos":"G","bench":false,"rk":339,"val":5.63},{"Player ID + Player Name":"75241-82357:Greyson Sigg","Id":"75241-82357","":"","Roster Position":"G","name":"Greyson Sigg","sal":8700,"fppg":63.41,"pos":"G","bench":false,"rk":181,"val":7.29},{"Player ID + Player Name":"75241-78890:Vaughn Taylor","Id":"75241-78890","":"","Roster Position":"G","name":"Vaughn Taylor","sal":8600,"fppg":58.57,"pos":"G","bench":false,"rk":393,"val":6.81},{"Player ID + Player Name":"75241-78154:Emiliano Grillo","Id":"75241-78154","":"","Roster Position":"G","name":"Emiliano Grillo","sal":8600,"fppg":47.18,"pos":"G","bench":false,"rk":138,"val":5.49},{"Player ID + Player Name":"75241-78185:Nick Hardy","Id":"75241-78185","":"","Roster Position":"G","name":"Nick Hardy","sal":8600,"fppg":49.91,"pos":"G","bench":true,"rk":465,"val":5.8},{"Player ID + Player Name":"75241-78782:Chase Seiffert","Id":"75241-78782","":"","Roster Position":"G","name":"Chase Seiffert","sal":8600,"fppg":62.59,"pos":"G","bench":false,"rk":398,"val":7.28},{"Player ID + Player Name":"75241-79954:Hank Lebioda","Id":"75241-79954","":"","Roster Position":"G","name":"Hank Lebioda","sal":8500,"fppg":41.77,"pos":"G","bench":false,"rk":277,"val":4.91},{"Player ID + Player Name":"75241-78951:Matt Wallace","Id":"75241-78951","":"","Roster Position":"G","name":"Matt Wallace","sal":8500,"fppg":35.06,"pos":"G","bench":false,"rk":134,"val":4.12},{"Player ID + Player Name":"75241-78698:Andrew Putnam","Id":"75241-78698","":"","Roster Position":"G","name":"Andrew Putnam","sal":8500,"fppg":55.41,"pos":"G","bench":false,"rk":151,"val":6.52},{"Player ID + Player Name":"75241-77816:Ryan Armour","Id":"75241-77816","":"","Roster Position":"G","name":"Ryan Armour","sal":8500,"fppg":51.2,"pos":"G","bench":false,"rk":329,"val":6.02},{"Player ID + Player Name":"75241-77884:Joseph Bramlett","Id":"75241-77884","":"","Roster Position":"G","name":"Joseph Bramlett","sal":8400,"fppg":50.66,"pos":"G","bench":false,"rk":234,"val":6.03},{"Player ID + Player Name":"75241-101765:Lee Hodges","Id":"75241-101765","":"","Roster Position":"G","name":"Lee Hodges","sal":8400,"fppg":52.18,"pos":"G","bench":false,"rk":216,"val":6.21},{"Player ID + Player Name":"75241-117701:Dylan Wu","Id":"75241-117701","":"","Roster Position":"G","name":"Dylan Wu","sal":8400,"fppg":52.02,"pos":"G","bench":false,"rk":392,"val":6.19},{"Player ID + Player Name":"75241-116974:Vince Whaley","Id":"75241-116974","":"","Roster Position":"G","name":"Vince Whaley","sal":8400,"fppg":59.96,"pos":"G","bench":false,"rk":2000,"val":7.14},{"Player ID + Player Name":"75241-78856:Robert Streb","Id":"75241-78856","":"","Roster Position":"G","name":"Robert Streb","sal":8300,"fppg":51.37,"pos":"G","bench":false,"rk":148,"val":6.19},{"Player ID + Player Name":"75241-78118:Brice Garnett","Id":"75241-78118","":"","Roster Position":"G","name":"Brice Garnett","sal":8300,"fppg":45.84,"pos":"G","bench":false,"rk":316,"val":5.52},{"Player ID + Player Name":"75241-79537:Justin Lower","Id":"75241-79537","":"","Roster Position":"G","name":"Justin Lower","sal":8300,"fppg":49.05,"pos":"G","bench":false,"rk":441,"val":5.91},{"Player ID + Player Name":"75241-80560:Alex Smalley","Id":"75241-80560","":"","Roster Position":"G","name":"Alex Smalley","sal":8300,"fppg":56.28,"pos":"G","bench":false,"rk":205,"val":6.78},{"Player ID + Player Name":"75241-78897:Michael Thompson","Id":"75241-78897","":"","Roster Position":"G","name":"Michael Thompson","sal":8200,"fppg":57.19,"pos":"G","bench":false,"rk":202,"val":6.97},{"Player ID + Player Name":"75241-78245:John Huh","Id":"75241-78245","":"","Roster Position":"G","name":"John Huh","sal":8200,"fppg":56.58,"pos":"G","bench":false,"rk":282,"val":6.9},{"Player ID + Player Name":"75241-78525:Graeme McDowell","Id":"75241-78525","":"","Roster Position":"G","name":"Graeme McDowell","sal":8200,"fppg":49.15,"pos":"G","bench":false,"rk":374,"val":5.99},{"Player ID + Player Name":"75241-78576:Trey Mullinax","Id":"75241-78576","":"","Roster Position":"G","name":"Trey Mullinax","sal":8200,"fppg":47.49,"pos":"G","bench":false,"rk":317,"val":5.79},{"Player ID + Player Name":"75241-78357:Kurt Kitayama","Id":"75241-78357","":"","Roster Position":"G","name":"Kurt Kitayama","sal":8100,"fppg":47.63,"pos":"G","bench":false,"rk":208,"val":5.88},{"Player ID + Player Name":"75241-101528:Hayden Buckley","Id":"75241-101528","":"","Roster Position":"G","name":"Hayden Buckley","sal":8100,"fppg":53.14,"pos":"G","bench":false,"rk":227,"val":6.56},{"Player ID + Player Name":"75241-78769:Adam Schenk","Id":"75241-78769","":"","Roster Position":"G","name":"Adam Schenk","sal":8100,"fppg":44.64,"pos":"G","bench":false,"rk":191,"val":5.51},{"Player ID + Player Name":"75241-78268:Stephan Jaeger","Id":"75241-78268","":"","Roster Position":"G","name":"Stephan Jaeger","sal":8100,"fppg":41.13,"pos":"G","bench":false,"rk":197,"val":5.08},{"Player ID + Player Name":"75241-78919:Peter Uihlein","Id":"75241-78919","":"","Roster Position":"G","name":"Peter Uihlein","sal":8000,"fppg":53.25,"pos":"G","bench":false,"rk":299,"val":6.66},{"Player ID + Player Name":"75241-107347:Callum Tarren","Id":"75241-107347","":"","Roster Position":"G","name":"Callum Tarren","sal":8000,"fppg":40.68,"pos":"G","bench":false,"rk":415,"val":5.09},{"Player ID + Player Name":"75241-78491:Peter Malnati","Id":"75241-78491","":"","Roster Position":"G","name":"Peter Malnati","sal":8000,"fppg":55.81,"pos":"G","bench":false,"rk":273,"val":6.98},{"Player ID + Player Name":"75241-78500:Ben Martin","Id":"75241-78500","":"","Roster Position":"G","name":"Ben Martin","sal":8000,"fppg":58.52,"pos":"G","bench":false,"rk":337,"val":7.31},{"Player ID + Player Name":"75241-78169:James Hahn","Id":"75241-78169","":"","Roster Position":"G","name":"James Hahn","sal":7900,"fppg":40.02,"pos":"G","bench":false,"rk":327,"val":5.07},{"Player ID + Player Name":"75241-101764:Ben Griffin","Id":"75241-101764","":"","Roster Position":"G","name":"Ben Griffin","sal":7900,"fppg":null,"pos":"G","bench":false,"rk":2000,"val":0},{"Player ID + Player Name":"75241-119463:Patrick Flavin","Id":"75241-119463","":"","Roster Position":"G","name":"Patrick Flavin","sal":7900,"fppg":77.43,"pos":"G","bench":false,"rk":646,"val":9.8},{"Player ID + Player Name":"75241-77823:Aaron Baddeley","Id":"75241-77823","":"","Roster Position":"G","name":"Aaron Baddeley","sal":7900,"fppg":58.86,"pos":"G","bench":false,"rk":688,"val":7.45},{"Player ID + Player Name":"75241-78918:Kevin Tway","Id":"75241-78918","":"","Roster Position":"G","name":"Kevin Tway","sal":7800,"fppg":45,"pos":"G","bench":false,"rk":269,"val":5.77},{"Player ID + Player Name":"75241-78719:Chez Reavie","Id":"75241-78719","":"","Roster Position":"G","name":"Chez Reavie","sal":7800,"fppg":46.05,"pos":"G","bench":false,"rk":232,"val":5.9},{"Player ID + Player Name":"75241-78020:Luke Donald","Id":"75241-78020","":"","Roster Position":"G","name":"Luke Donald","sal":7800,"fppg":50.98,"pos":"G","bench":false,"rk":519,"val":6.54},{"Player ID + Player Name":"75241-78310:Sung Kang","Id":"75241-78310","":"","Roster Position":"G","name":"Sung Kang","sal":7800,"fppg":49.86,"pos":"G","bench":false,"rk":2000,"val":6.39},{"Player ID + Player Name":"75241-77832:Paul Barjon","Id":"75241-77832","":"","Roster Position":"G","name":"Paul Barjon","sal":7700,"fppg":46.13,"pos":"G","bench":false,"rk":349,"val":5.99},{"Player ID + Player Name":"75241-78162:Bill Haas","Id":"75241-78162","":"","Roster Position":"G","name":"Bill Haas","sal":7700,"fppg":52.21,"pos":"G","bench":false,"rk":567,"val":6.78},{"Player ID + Player Name":"75241-82360:Andrew Novak","Id":"75241-82360","":"","Roster Position":"G","name":"Andrew Novak","sal":7700,"fppg":51.94,"pos":"G","bench":false,"rk":361,"val":6.74},{"Player ID + Player Name":"75241-116965:Bo Hoag","Id":"75241-116965","":"","Roster Position":"G","name":"Bo Hoag","sal":7700,"fppg":37.92,"pos":"G","bench":false,"rk":403,"val":4.92},{"Player ID + Player Name":"75241-79671:Ben Kohles","Id":"75241-79671","":"","Roster Position":"G","name":"Ben Kohles","sal":7600,"fppg":51.16,"pos":"G","bench":false,"rk":497,"val":6.73},{"Player ID + Player Name":"75241-77897:Wesley Bryan","Id":"75241-77897","":"","Roster Position":"G","name":"Wesley Bryan","sal":7600,"fppg":45.71,"pos":"G","bench":false,"rk":524,"val":6.01},{"Player ID + Player Name":"75241-78942:Camilo Villegas","Id":"75241-78942","":"","Roster Position":"G","name":"Camilo Villegas","sal":7600,"fppg":50.02,"pos":"G","bench":false,"rk":413,"val":6.58},{"Player ID + Player Name":"75241-78811:Roger Sloan","Id":"75241-78811","":"","Roster Position":"G","name":"Roger Sloan","sal":7600,"fppg":44.45,"pos":"G","bench":false,"rk":284,"val":5.85},{"Player ID + Player Name":"75241-156418:Scott Gutschewski","Id":"75241-156418","":"","Roster Position":"G","name":"Scott Gutschewski","sal":7500,"fppg":50.85,"pos":"G","bench":false,"rk":635,"val":6.78},{"Player ID + Player Name":"75241-78366:Satoshi Kodaira","Id":"75241-78366","":"","Roster Position":"G","name":"Satoshi Kodaira","sal":7500,"fppg":57.13,"pos":"G","bench":false,"rk":300,"val":7.62},{"Player ID + Player Name":"75241-80336:Seth Reeves","Id":"75241-80336","":"","Roster Position":"G","name":"Seth Reeves","sal":7500,"fppg":47.27,"pos":"G","bench":false,"rk":385,"val":6.3},{"Player ID + Player Name":"75241-78034:Jason Dufner","Id":"75241-78034","":"","Roster Position":"G","name":"Jason Dufner","sal":7500,"fppg":40.59,"pos":"G","bench":false,"rk":525,"val":5.41},{"Player ID + Player Name":"75241-161547:Max McGreevy","Id":"75241-161547","":"","Roster Position":"G","name":"Max McGreevy","sal":7400,"fppg":47.94,"pos":"G","bench":false,"rk":240,"val":6.48},{"Player ID + Player Name":"75241-78168:Brandon Hagy","Id":"75241-78168","":"","Roster Position":"G","name":"Brandon Hagy","sal":7400,"fppg":41.52,"pos":"G","bench":false,"rk":294,"val":5.61},{"Player ID + Player Name":"75241-78972:Richy Werenski","Id":"75241-78972","":"","Roster Position":"G","name":"Richy Werenski","sal":7400,"fppg":40.51,"pos":"G","bench":false,"rk":301,"val":5.47},{"Player ID + Player Name":"75241-155106:Curtis Thompson","Id":"75241-155106","":"","Roster Position":"G","name":"Curtis Thompson","sal":7400,"fppg":46.77,"pos":"G","bench":false,"rk":440,"val":6.32},{"Player ID + Player Name":"75241-77824:Sang-Moon Bae","Id":"75241-77824","":"","Roster Position":"G","name":"Sang-Moon Bae","sal":7300,"fppg":46.53,"pos":"G","bench":false,"rk":2000,"val":6.37},{"Player ID + Player Name":"75241-78134:Michael Gligic","Id":"75241-78134","":"","Roster Position":"G","name":"Michael Gligic","sal":7300,"fppg":45.1,"pos":"G","bench":false,"rk":528,"val":6.18},{"Player ID + Player Name":"75241-77894:Scott Brown","Id":"75241-77894","":"","Roster Position":"G","name":"Scott Brown","sal":7300,"fppg":54.3,"pos":"G","bench":false,"rk":612,"val":7.44},{"Player ID + Player Name":"75241-77967:Austin Cook","Id":"75241-77967","":"","Roster Position":"G","name":"Austin Cook","sal":7300,"fppg":42.94,"pos":"G","bench":false,"rk":442,"val":5.88},{"Player ID + Player Name":"75241-102671:Bryson Nimmer","Id":"75241-102671","":"","Roster Position":"G","name":"Bryson Nimmer","sal":7200,"fppg":56.2,"pos":"G","bench":false,"rk":688,"val":7.81},{"Player ID + Player Name":"75241-77866:Ryan Blaum","Id":"75241-77866","":"","Roster Position":"G","name":"Ryan Blaum","sal":7200,"fppg":35.11,"pos":"G","bench":false,"rk":676,"val":4.88},{"Player ID + Player Name":"75241-82996:Joshua Creel","Id":"75241-82996","":"","Roster Position":"G","name":"Joshua Creel","sal":7200,"fppg":31.81,"pos":"G","bench":false,"rk":370,"val":4.42},{"Player ID + Player Name":"75241-78137:Fabian Gomez","Id":"75241-78137","":"","Roster Position":"G","name":"Fabian Gomez","sal":7200,"fppg":29.02,"pos":"G","bench":false,"rk":726,"val":4.03},{"Player ID + Player Name":"75241-77821:Arjun Atwal","Id":"75241-77821","":"","Roster Position":"G","name":"Arjun Atwal","sal":7200,"fppg":44.4,"pos":"G","bench":false,"rk":1679,"val":6.17},{"Player ID + Player Name":"75241-78598:Seung-Yul Noh","Id":"75241-78598","":"","Roster Position":"G","name":"Seung-Yul Noh","sal":7100,"fppg":48.18,"pos":"G","bench":false,"rk":2000,"val":6.79},{"Player ID + Player Name":"75241-78120:Robert Garrigus","Id":"75241-78120","":"","Roster Position":"G","name":"Robert Garrigus","sal":7100,"fppg":71.57,"pos":"G","bench":false,"rk":1053,"val":10.08},{"Player ID + Player Name":"75241-79689:Jim Knous","Id":"75241-79689","":"","Roster Position":"G","name":"Jim Knous","sal":7100,"fppg":58.53,"pos":"G","bench":false,"rk":787,"val":8.24},{"Player ID + Player Name":"75241-78684:D.A. Points","Id":"75241-78684","":"","Roster Position":"G","name":"D.A. Points","sal":7100,"fppg":48.05,"pos":"G","bench":false,"rk":1724,"val":6.77},{"Player ID + Player Name":"75241-161550:Turk Pettit","Id":"75241-161550","":"","Roster Position":"G","name":"Turk Pettit","sal":7000,"fppg":26.4,"pos":"G","bench":false,"rk":766,"val":3.77},{"Player ID + Player Name":"75241-77836:Ricky Barnes","Id":"75241-77836","":"","Roster Position":"G","name":"Ricky Barnes","sal":7000,"fppg":36.58,"pos":"G","bench":false,"rk":1262,"val":5.23},{"Player ID + Player Name":"75241-161549:Jared Wolfe","Id":"75241-161549","":"","Roster Position":"G","name":"Jared Wolfe","sal":7000,"fppg":42.55,"pos":"G","bench":false,"rk":502,"val":6.08},{"Player ID + Player Name":"75241-78110:Tommy Gainey","Id":"75241-78110","":"","Roster Position":"G","name":"Tommy Gainey","sal":7000,"fppg":40.6,"pos":"G","bench":false,"rk":556,"val":5.8},{"Player ID + Player Name":"75241-78889:Nick Taylor","Id":"75241-78889","":"","Roster Position":"G","name":"Nick Taylor","sal":7000,"fppg":55.69,"pos":"G","bench":false,"rk":256,"val":7.96},{"Player ID + Player Name":"75241-79657:Ben Willman","Id":"75241-79657","":"","Roster Position":"G","name":"Ben Willman","sal":7000,"fppg":2.2,"pos":"G","bench":false,"rk":1724,"val":0.31},{"Player ID + Player Name":"75241-77867:Jonas Blixt","Id":"75241-77867","":"","Roster Position":"G","name":"Jonas Blixt","sal":7000,"fppg":28.11,"pos":"G","bench":false,"rk":1337,"val":4.02},{"Player ID + Player Name":"75241-78378:Kelly Kraft","Id":"75241-78378","":"","Roster Position":"G","name":"Kelly Kraft","sal":7000,"fppg":36.14,"pos":"G","bench":false,"rk":719,"val":5.16},{"Player ID + Player Name":"75241-110900:Isidro Benitez","Id":"75241-110900","":"","Roster Position":"G","name":"Isidro Benitez","sal":7000,"fppg":19.9,"pos":"G","bench":false,"rk":1256,"val":2.84},{"Player ID + Player Name":"75241-78909:D.J. Trahan","Id":"75241-78909","":"","Roster Position":"G","name":"D.J. Trahan","sal":7000,"fppg":48.08,"pos":"G","bench":false,"rk":1411,"val":6.87},{"Player ID + Player Name":"75241-78910:Martin Trainer","Id":"75241-78910","":"","Roster Position":"G","name":"Martin Trainer","sal":7000,"fppg":41.05,"pos":"G","bench":false,"rk":478,"val":5.86},{"Player ID + Player Name":"75241-78927:Dawie Van der Walt","Id":"75241-78927","":"","Roster Position":"G","name":"Dawie Van der Walt","sal":7000,"fppg":35.43,"pos":"G","bench":false,"rk":2000,"val":5.06},{"Player ID + Player Name":"75241-77905:Jonathan Byrd","Id":"75241-77905","":"","Roster Position":"G","name":"Jonathan Byrd","sal":7000,"fppg":52.06,"pos":"G","bench":false,"rk":569,"val":7.44},{"Player ID + Player Name":"75241-78946:Johnson Wagner","Id":"75241-78946","":"","Roster Position":"G","name":"Johnson Wagner","sal":7000,"fppg":67.55,"pos":"G","bench":false,"rk":1468,"val":9.65},{"Player ID + Player Name":"75241-77929:Greg Chalmers","Id":"75241-77929","":"","Roster Position":"G","name":"Greg Chalmers","sal":7000,"fppg":56.3,"pos":"G","bench":false,"rk":1442,"val":8.04},{"Player ID + Player Name":"75241-78449:David Lingmerth","Id":"75241-78449","":"","Roster Position":"G","name":"David Lingmerth","sal":7000,"fppg":76.3,"pos":"G","bench":false,"rk":633,"val":10.9},{"Player ID + Player Name":"75241-78195:David Hearn","Id":"75241-78195","":"","Roster Position":"G","name":"David Hearn","sal":7000,"fppg":37.22,"pos":"G","bench":false,"rk":867,"val":5.32},{"Player ID + Player Name":"75241-78209:Mark Hensby","Id":"75241-78209","":"","Roster Position":"G","name":"Mark Hensby","sal":7000,"fppg":55.8,"pos":"G","bench":false,"rk":975,"val":7.97},{"Player ID + Player Name":"75241-79503:Richard S Johnson","Id":"75241-79503","":"","Roster Position":"G","name":"Richard S Johnson","sal":7000,"fppg":25.4,"pos":"G","bench":false,"rk":2000,"val":3.63},{"Player ID + Player Name":"75241-77975:Ben Crane","Id":"75241-77975","":"","Roster Position":"G","name":"Ben Crane","sal":7000,"fppg":29.77,"pos":"G","bench":false,"rk":1724,"val":4.25},{"Player ID + Player Name":"75241-80543:Armando Favela","Id":"75241-80543","":"","Roster Position":"G","name":"Armando Favela","sal":7000,"fppg":16.4,"pos":"G","bench":false,"rk":1383,"val":2.34},{"Player ID + Player Name":"75241-169654:Jose Cristobal Islas","Id":"75241-169654","":"","Roster Position":"G","name":"Jose Cristobal Islas","sal":7000,"fppg":null,"pos":"G","bench":false,"rk":1724,"val":0},{"Player ID + Player Name":"75241-169655:Santiago De la Fuente","Id":"75241-169655","":"","Roster Position":"G","name":"Santiago De la Fuente","sal":7000,"fppg":null,"pos":"G","bench":false,"rk":1724,"val":0},{"Player ID + Player Name":"75241-169653:Manuel Inman","Id":"75241-169653","":"","Roster Position":"G","name":"Manuel Inman","sal":7000,"fppg":null,"pos":"G","bench":false,"rk":2000,"val":0},{"Player ID + Player Name":"75241-169656:Jose Antonio Safa","Id":"75241-169656","":"","Roster Position":"G","name":"Jose Antonio Safa","sal":7000,"fppg":null,"pos":"G","bench":false,"rk":1724,"val":0},{"Player ID + Player Name":"75241-78013:Roberto Diaz","Id":"75241-78013","":"","Roster Position":"G","name":"Roberto Diaz","sal":7000,"fppg":76.5,"pos":"G","bench":false,"rk":624,"val":10.93},{"Player ID + Player Name":"75241-165827:Jeffrey Kang","Id":"75241-165827","":"","Roster Position":"G","name":"Jeffrey Kang","sal":7000,"fppg":18.1,"pos":"G","bench":false,"rk":1724,"val":2.59},{"Player ID + Player Name":"75241-78026:Brett Drewitt","Id":"75241-78026","":"","Roster Position":"G","name":"Brett Drewitt","sal":7000,"fppg":40.61,"pos":"G","bench":false,"rk":532,"val":5.8},{"Player ID + Player Name":"75241-78809:David Skinns","Id":"75241-78809","":"","Roster Position":"G","name":"David Skinns","sal":7000,"fppg":40.92,"pos":"G","bench":false,"rk":324,"val":5.85},{"Player ID + Player Name":"75241-103128:Alvaro Ortiz","Id":"75241-103128","":"","Roster Position":"G","name":"Alvaro Ortiz","sal":7000,"fppg":-2.4,"pos":"G","bench":false,"rk":2000,"val":-0.34},{"Player ID + Player Name":"75241-78052:Derek Ernst","Id":"75241-78052","":"","Roster Position":"G","name":"Derek Ernst","sal":7000,"fppg":44.85,"pos":"G","bench":false,"rk":1545,"val":6.41},{"Player ID + Player Name":"75241-78060:Matt Every","Id":"75241-78060","":"","Roster Position":"G","name":"Matt Every","sal":7000,"fppg":29.5,"pos":"G","bench":false,"rk":1715,"val":4.21},{"Player ID + Player Name":"75241-78582:Grayson Murray","Id":"75241-78582","":"","Roster Position":"G","name":"Grayson Murray","sal":7000,"fppg":28.13,"pos":"G","bench":false,"rk":813,"val":4.02},{"Player ID + Player Name":"75241-117242:Bo Van Pelt","Id":"75241-117242","":"","Roster Position":"G","name":"Bo Van Pelt","sal":7000,"fppg":36.62,"pos":"G","bench":false,"rk":433,"val":5.23}]},{"sport":"PGA","league":"Yahoo","type":"Classic","about":"Mexico Open at Vidanta","games":[{"date":"04/28/2022","day":"Thursday","time":"05:45AM","zone":"EDT","filter":""}],"players":[{"name":"Jon Rahm","sal":53,"fppg":80.7,"pos":"G","bench":false,"rk":2,"val":1522.64,"id":"golf.p.18796$golf.g.2022671 - Jon Rahm"},{"name":"Abraham Ancer","sal":44,"fppg":59.9,"pos":"G","bench":false,"rk":20,"val":1361.36,"id":"golf.p.16893$golf.g.2022671 - Abraham Ancer"},{"name":"Tony Finau","sal":45,"fppg":56,"pos":"G","bench":false,"rk":25,"val":1244.44,"id":"golf.p.8805$golf.g.2022671 - Tony Finau"},{"name":"Kevin Na","sal":42,"fppg":57.3,"pos":"G","bench":false,"rk":32,"val":1364.29,"id":"golf.p.3962$golf.g.2022671 - Kevin Na"},{"name":"Patrick Reed","sal":42,"fppg":52,"pos":"G","bench":false,"rk":33,"val":1238.1,"id":"golf.p.11250$golf.g.2022671 - Patrick Reed"},{"name":"Cameron Tringale","sal":42,"fppg":64.1,"pos":"G","bench":false,"rk":49,"val":1526.19,"id":"golf.p.10182$golf.g.2022671 - Cameron Tringale"},{"name":"Matt Jones","sal":36,"fppg":57.9,"pos":"G","bench":false,"rk":67,"val":1608.33,"id":"golf.p.4932$golf.g.2022671 - Matt Jones"},{"name":"Sebastian Munoz","sal":33,"fppg":56.5,"pos":"G","bench":false,"rk":73,"val":1712.12,"id":"golf.p.20691$golf.g.2022671 - Sebastian Munoz"},{"name":"Anirban Lahiri","sal":35,"fppg":46.2,"pos":"G","bench":false,"rk":85,"val":1320,"id":"golf.p.10574$golf.g.2022671 - Anirban Lahiri"},{"name":"Carlos Ortiz","sal":35,"fppg":51.6,"pos":"G","bench":false,"rk":90,"val":1474.29,"id":"golf.p.10730$golf.g.2022671 - Carlos Ortiz"},{"name":"Chris Kirk","sal":38,"fppg":62.6,"pos":"G","bench":false,"rk":92,"val":1647.37,"id":"golf.p.9268$golf.g.2022671 - Chris Kirk"},{"name":"Aaron Wise","sal":37,"fppg":62.6,"pos":"G","bench":false,"rk":93,"val":1691.89,"id":"golf.p.20980$golf.g.2022671 - Aaron Wise"},{"name":"Gary Woodland","sal":37,"fppg":53.1,"pos":"G","bench":false,"rk":96,"val":1435.14,"id":"golf.p.9366$golf.g.2022671 - Gary Woodland"},{"name":"Kevin Streelman","sal":33,"fppg":52.6,"pos":"G","bench":false,"rk":98,"val":1593.94,"id":"golf.p.6074$golf.g.2022671 - Kevin Streelman"},{"name":"Cameron Champ","sal":34,"fppg":40.2,"pos":"G","bench":false,"rk":104,"val":1182.35,"id":"golf.p.21805$golf.g.2022671 - Cameron Champ"},{"name":"Lanto Griffin","sal":34,"fppg":56.9,"pos":"G","bench":false,"rk":107,"val":1673.53,"id":"golf.p.11626$golf.g.2022671 - Lanto Griffin"},{"name":"Chad Ramey","sal":30,"fppg":53.6,"pos":"G","bench":false,"rk":119,"val":1786.67,"id":"golf.p.19920$golf.g.2022671 - Chad Ramey"},{"name":"Aaron Rai","sal":26,"fppg":53.2,"pos":"G","bench":false,"rk":122,"val":2046.15,"id":"golf.p.20884$golf.g.2022671 - Aaron Rai"},{"name":"Sahith Theegala","sal":33,"fppg":59.8,"pos":"G","bench":false,"rk":125,"val":1812.12,"id":"golf.p.21421$golf.g.2022671 - Sahith Theegala"},{"name":"Rafa Cabrera Bello","sal":29,"fppg":46.2,"pos":"G","bench":false,"rk":126,"val":1593.1,"id":"golf.p.5021$golf.g.2022671 - Rafa Cabrera Bello"},{"name":"Matt Wallace","sal":25,"fppg":29.7,"pos":"G","bench":false,"rk":134,"val":1188,"id":"golf.p.20651$golf.g.2022671 - Matt Wallace"},{"name":"C.T. Pan","sal":29,"fppg":54.9,"pos":"G","bench":false,"rk":136,"val":1893.1,"id":"golf.p.9061$golf.g.2022671 - C.T. Pan"},{"name":"Emiliano Grillo","sal":31,"fppg":41.8,"pos":"G","bench":false,"rk":138,"val":1348.39,"id":"golf.p.11523$golf.g.2022671 - Emiliano Grillo"},{"name":"Kramer Hickok","sal":25,"fppg":45.6,"pos":"G","bench":false,"rk":143,"val":1824,"id":"golf.p.20681$golf.g.2022671 - Kramer Hickok"},{"name":"Robert Streb","sal":25,"fppg":48.6,"pos":"G","bench":false,"rk":148,"val":1944,"id":"golf.p.11275$golf.g.2022671 - Robert Streb"},{"name":"Andrew Putnam","sal":25,"fppg":52.4,"pos":"G","bench":false,"rk":151,"val":2096,"id":"golf.p.11153$golf.g.2022671 - Andrew Putnam"},{"name":"Brendon Todd","sal":31,"fppg":53.3,"pos":"G","bench":false,"rk":156,"val":1719.35,"id":"golf.p.9270$golf.g.2022671 - Brendon Todd"},{"name":"Taylor Moore","sal":27,"fppg":46.3,"pos":"G","bench":false,"rk":160,"val":1714.81,"id":"golf.p.20945$golf.g.2022671 - Taylor Moore"},{"name":"J.T. Poston","sal":25,"fppg":41.3,"pos":"G","bench":false,"rk":168,"val":1652,"id":"golf.p.20845$golf.g.2022671 - J.T. Poston"},{"name":"Adam Svensson","sal":25,"fppg":51.5,"pos":"G","bench":false,"rk":176,"val":2060,"id":"golf.p.14037$golf.g.2022671 - Adam Svensson"},{"name":"Adam Long","sal":24,"fppg":54.1,"pos":"G","bench":false,"rk":177,"val":2254.17,"id":"golf.p.11698$golf.g.2022671 - Adam Long"},{"name":"Greyson Sigg","sal":26,"fppg":57.6,"pos":"G","bench":false,"rk":181,"val":2215.38,"id":"golf.p.22208$golf.g.2022671 - Greyson Sigg"},{"name":"Russell Knox","sal":32,"fppg":60.1,"pos":"G","bench":false,"rk":183,"val":1878.13,"id":"golf.p.10129$golf.g.2022671 - Russell Knox"},{"name":"Doug Ghim","sal":31,"fppg":50.5,"pos":"G","bench":false,"rk":184,"val":1629.03,"id":"golf.p.22376$golf.g.2022671 - Doug Ghim"},{"name":"Davis Riley","sal":29,"fppg":53,"pos":"G","bench":false,"rk":185,"val":1827.59,"id":"golf.p.19934$golf.g.2022671 - Davis Riley"},{"name":"Charles Howell III","sal":31,"fppg":54.9,"pos":"G","bench":false,"rk":189,"val":1770.97,"id":"golf.p.577$golf.g.2022671 - Charles Howell III"},{"name":"Pat Perez","sal":28,"fppg":46.9,"pos":"G","bench":false,"rk":190,"val":1675,"id":"golf.p.3462$golf.g.2022671 - Pat Perez"},{"name":"Adam Schenk","sal":24,"fppg":39.8,"pos":"G","bench":false,"rk":191,"val":1658.33,"id":"golf.p.19122$golf.g.2022671 - Adam Schenk"},{"name":"Scott Stallings","sal":24,"fppg":52.4,"pos":"G","bench":false,"rk":195,"val":2183.33,"id":"golf.p.9183$golf.g.2022671 - Scott Stallings"},{"name":"Stephan Jaeger","sal":24,"fppg":36.5,"pos":"G","bench":false,"rk":197,"val":1520.83,"id":"golf.p.12995$golf.g.2022671 - Stephan Jaeger"},{"name":"Michael Thompson","sal":27,"fppg":53.3,"pos":"G","bench":false,"rk":202,"val":1974.07,"id":"golf.p.9607$golf.g.2022671 - Michael Thompson"},{"name":"David Lipsky","sal":24,"fppg":46.2,"pos":"G","bench":false,"rk":204,"val":1925,"id":"golf.p.12367$golf.g.2022671 - David Lipsky"},{"name":"Alex Smalley","sal":27,"fppg":52.3,"pos":"G","bench":false,"rk":205,"val":1937.04,"id":"golf.p.18385$golf.g.2022671 - Alex Smalley"},{"name":"Kurt Kitayama","sal":24,"fppg":41.7,"pos":"G","bench":false,"rk":208,"val":1737.5,"id":"golf.p.20654$golf.g.2022671 - Kurt Kitayama"},{"name":"Lee Hodges","sal":27,"fppg":48.2,"pos":"G","bench":false,"rk":216,"val":1785.19,"id":"golf.p.22885$golf.g.2022671 - Lee Hodges"},{"name":"Hayden Buckley","sal":23,"fppg":48.4,"pos":"G","bench":false,"rk":227,"val":2104.35,"id":"golf.p.22847$golf.g.2022671 - Hayden Buckley"},{"name":"Chez Reavie","sal":23,"fppg":41,"pos":"G","bench":false,"rk":232,"val":1782.61,"id":"golf.p.5000$golf.g.2022671 - Chez Reavie"},{"name":"Joseph Bramlett","sal":23,"fppg":46.4,"pos":"G","bench":false,"rk":234,"val":2017.39,"id":"golf.p.11152$golf.g.2022671 - Joseph Bramlett"},{"name":"Kiradech Aphibarnrat","sal":20,"fppg":45.8,"pos":"G","bench":false,"rk":237,"val":2290,"id":"golf.p.10260$golf.g.2022671 - Kiradech Aphibarnrat"},{"name":"Max McGreevy","sal":20,"fppg":43.1,"pos":"G","bench":false,"rk":240,"val":2155,"id":"golf.p.22014$golf.g.2022671 - Max McGreevy"},{"name":"Brian Stuard","sal":20,"fppg":46.8,"pos":"G","bench":false,"rk":241,"val":2340,"id":"golf.p.9664$golf.g.2022671 - Brian Stuard"},{"name":"Nick Taylor","sal":23,"fppg":51.1,"pos":"G","bench":false,"rk":256,"val":2221.74,"id":"golf.p.4027$golf.g.2022671 - Nick Taylor"},{"name":"Patrick Rodgers","sal":20,"fppg":47.8,"pos":"G","bench":false,"rk":265,"val":2390,"id":"golf.p.12885$golf.g.2022671 - Patrick Rodgers"},{"name":"Kevin Tway","sal":20,"fppg":41,"pos":"G","bench":false,"rk":269,"val":2050,"id":"golf.p.9713$golf.g.2022671 - Kevin Tway"},{"name":"Peter Malnati","sal":20,"fppg":50.8,"pos":"G","bench":false,"rk":273,"val":2540,"id":"golf.p.11369$golf.g.2022671 - Peter Malnati"},{"name":"Mark Hubbard","sal":21,"fppg":56.9,"pos":"G","bench":false,"rk":274,"val":2709.52,"id":"golf.p.14062$golf.g.2022671 - Mark Hubbard"},{"name":"Scott Piercy","sal":20,"fppg":43.3,"pos":"G","bench":false,"rk":275,"val":2165,"id":"golf.p.4726$golf.g.2022671 - Scott Piercy"},{"name":"Hank Lebioda","sal":20,"fppg":37.3,"pos":"G","bench":false,"rk":277,"val":1865,"id":"golf.p.21594$golf.g.2022671 - Hank Lebioda"},{"name":"Wyndham Clark","sal":20,"fppg":51.2,"pos":"G","bench":false,"rk":279,"val":2560,"id":"golf.p.21868$golf.g.2022671 - Wyndham Clark"},{"name":"Danny Lee","sal":20,"fppg":45.8,"pos":"G","bench":false,"rk":281,"val":2290,"id":"golf.p.8922$golf.g.2022671 - Danny Lee"},{"name":"John Huh","sal":20,"fppg":53.6,"pos":"G","bench":false,"rk":282,"val":2680,"id":"golf.p.11092$golf.g.2022671 - John Huh"},{"name":"Roger Sloan","sal":20,"fppg":40.2,"pos":"G","bench":false,"rk":284,"val":2010,"id":"golf.p.11044$golf.g.2022671 - Roger Sloan"},{"name":"Brandon Hagy","sal":23,"fppg":36.5,"pos":"G","bench":false,"rk":294,"val":1586.96,"id":"golf.p.13038$golf.g.2022671 - Brandon Hagy"},{"name":"Peter Uihlein","sal":20,"fppg":47.4,"pos":"G","bench":false,"rk":299,"val":2370,"id":"golf.p.8623$golf.g.2022671 - Peter Uihlein"},{"name":"Satoshi Kodaira","sal":20,"fppg":48.3,"pos":"G","bench":false,"rk":300,"val":2415,"id":"golf.p.11663$golf.g.2022671 - Satoshi Kodaira"},{"name":"Richy Werenski","sal":20,"fppg":35.6,"pos":"G","bench":false,"rk":301,"val":1780,"id":"golf.p.18929$golf.g.2022671 - Richy Werenski"},{"name":"Nate Lashley","sal":20,"fppg":54.4,"pos":"G","bench":false,"rk":308,"val":2720,"id":"golf.p.8423$golf.g.2022671 - Nate Lashley"},{"name":"Austin Smotherman","sal":20,"fppg":47.9,"pos":"G","bench":false,"rk":312,"val":2395,"id":"golf.p.21440$golf.g.2022671 - Austin Smotherman"},{"name":"Brice Garnett","sal":20,"fppg":43.3,"pos":"G","bench":false,"rk":316,"val":2165,"id":"golf.p.8702$golf.g.2022671 - Brice Garnett"},{"name":"Trey Mullinax","sal":20,"fppg":44.3,"pos":"G","bench":false,"rk":317,"val":2215,"id":"golf.p.18555$golf.g.2022671 - Trey Mullinax"},{"name":"David Skinns","sal":20,"fppg":35.7,"pos":"G","bench":false,"rk":324,"val":1785,"id":"golf.p.5985$golf.g.2022671 - David Skinns"},{"name":"James Hahn","sal":20,"fppg":36.9,"pos":"G","bench":false,"rk":327,"val":1845,"id":"golf.p.10606$golf.g.2022671 - James Hahn"},{"name":"Ryan Armour","sal":20,"fppg":47.8,"pos":"G","bench":false,"rk":329,"val":2390,"id":"golf.p.3489$golf.g.2022671 - Ryan Armour"},{"name":"Ben Martin","sal":20,"fppg":50.5,"pos":"G","bench":false,"rk":337,"val":2525,"id":"golf.p.10185$golf.g.2022671 - Ben Martin"},{"name":"Brandon Wu","sal":20,"fppg":44,"pos":"G","bench":false,"rk":339,"val":2200,"id":"golf.p.22793$golf.g.2022671 - Brandon Wu"},{"name":"Paul Barjon","sal":20,"fppg":41.8,"pos":"G","bench":false,"rk":349,"val":2090,"id":"golf.p.21180$golf.g.2022671 - Paul Barjon"},{"name":"Andrew Novak","sal":20,"fppg":47.3,"pos":"G","bench":false,"rk":361,"val":2365,"id":"golf.p.22209$golf.g.2022671 - Andrew Novak"},{"name":"Joshua Creel","sal":20,"fppg":29.2,"pos":"G","bench":false,"rk":370,"val":1460,"id":"golf.p.21110$golf.g.2022671 - Joshua Creel"},{"name":"Graeme McDowell","sal":20,"fppg":43.9,"pos":"G","bench":false,"rk":374,"val":2195,"id":"golf.p.4127$golf.g.2022671 - Graeme McDowell"},{"name":"Seth Reeves","sal":20,"fppg":41.2,"pos":"G","bench":false,"rk":385,"val":2060,"id":"golf.p.21358$golf.g.2022671 - Seth Reeves"},{"name":"Dylan Wu","sal":20,"fppg":48.3,"pos":"G","bench":false,"rk":392,"val":2415,"id":"golf.p.23235$golf.g.2022671 - Dylan Wu"},{"name":"Vaughn Taylor","sal":20,"fppg":52.5,"pos":"G","bench":false,"rk":393,"val":2625,"id":"golf.p.994$golf.g.2022671 - Vaughn Taylor"},{"name":"Chase Seiffert","sal":21,"fppg":57.6,"pos":"G","bench":false,"rk":398,"val":2742.86,"id":"golf.p.13930$golf.g.2022671 - Chase Seiffert"},{"name":"Bo Hoag","sal":20,"fppg":35.3,"pos":"G","bench":false,"rk":403,"val":1765,"id":"golf.p.10497$golf.g.2022671 - Bo Hoag"},{"name":"Camilo Villegas","sal":20,"fppg":43.6,"pos":"G","bench":false,"rk":413,"val":2180,"id":"golf.p.7021$golf.g.2022671 - Camilo Villegas"},{"name":"Callum Tarren","sal":20,"fppg":35.9,"pos":"G","bench":false,"rk":415,"val":1795,"id":"golf.p.21340$golf.g.2022671 - Callum Tarren"},{"name":"Bo Van Pelt","sal":20,"fppg":34.5,"pos":"G","bench":false,"rk":433,"val":1725,"id":"golf.p.1685$golf.g.2022671 - Bo Van Pelt"},{"name":"Curtis Thompson","sal":20,"fppg":43.7,"pos":"G","bench":false,"rk":440,"val":2185,"id":"golf.p.18612$golf.g.2022671 - Curtis Thompson"},{"name":"Justin Lower","sal":20,"fppg":44,"pos":"G","bench":false,"rk":441,"val":2200,"id":"golf.p.14063$golf.g.2022671 - Justin Lower"},{"name":"Austin Cook","sal":20,"fppg":39.7,"pos":"G","bench":false,"rk":442,"val":1985,"id":"golf.p.18437$golf.g.2022671 - Austin Cook"},{"name":"Nick Hardy","sal":20,"fppg":45.3,"pos":"G","bench":false,"rk":465,"val":2265,"id":"golf.p.19933$golf.g.2022671 - Nick Hardy"},{"name":"Martin Trainer","sal":20,"fppg":35.7,"pos":"G","bench":false,"rk":478,"val":1785,"id":"golf.p.11845$golf.g.2022671 - Martin Trainer"},{"name":"Kevin Chappell","sal":20,"fppg":50.6,"pos":"G","bench":false,"rk":491,"val":2530,"id":"golf.p.9800$golf.g.2022671 - Kevin Chappell"},{"name":"Ben Kohles","sal":20,"fppg":46.2,"pos":"G","bench":false,"rk":497,"val":2310,"id":"golf.p.12996$golf.g.2022671 - Ben Kohles"},{"name":"Jared Wolfe","sal":20,"fppg":38.7,"pos":"G","bench":false,"rk":502,"val":1935,"id":"golf.p.17148$golf.g.2022671 - Jared Wolfe"},{"name":"Luke Donald","sal":20,"fppg":48.3,"pos":"G","bench":false,"rk":519,"val":2415,"id":"golf.p.2675$golf.g.2022671 - Luke Donald"},{"name":"Wesley Bryan","sal":23,"fppg":42.4,"pos":"G","bench":false,"rk":524,"val":1843.48,"id":"golf.p.20678$golf.g.2022671 - Wesley Bryan"},{"name":"Jason Dufner","sal":20,"fppg":35.3,"pos":"G","bench":false,"rk":525,"val":1765,"id":"golf.p.4269$golf.g.2022671 - Jason Dufner"},{"name":"Michael Gligic","sal":20,"fppg":41,"pos":"G","bench":false,"rk":528,"val":2050,"id":"golf.p.10727$golf.g.2022671 - Michael Gligic"},{"name":"Brett Drewitt","sal":20,"fppg":37.9,"pos":"G","bench":false,"rk":532,"val":1895,"id":"golf.p.17788$golf.g.2022671 - Brett Drewitt"},{"name":"Tommy Gainey","sal":20,"fppg":32.4,"pos":"G","bench":false,"rk":556,"val":1620,"id":"golf.p.9098$golf.g.2022671 - Tommy Gainey"},{"name":"Bill Haas","sal":20,"fppg":49.4,"pos":"G","bench":false,"rk":567,"val":2470,"id":"golf.p.3610$golf.g.2022671 - Bill Haas"},{"name":"Jonathan Byrd","sal":20,"fppg":48,"pos":"G","bench":false,"rk":569,"val":2400,"id":"golf.p.3623$golf.g.2022671 - Jonathan Byrd"},{"name":"Scott Brown","sal":20,"fppg":48.2,"pos":"G","bench":false,"rk":612,"val":2410,"id":"golf.p.8620$golf.g.2022671 - Scott Brown"},{"name":"Roberto Diaz","sal":22,"fppg":78.4,"pos":"G","bench":false,"rk":624,"val":3563.64,"id":"golf.p.12839$golf.g.2022671 - Roberto Diaz"},{"name":"David Lingmerth","sal":22,"fppg":69.4,"pos":"G","bench":false,"rk":633,"val":3154.55,"id":"golf.p.11270$golf.g.2022671 - David Lingmerth"},{"name":"Scott Gutschewski","sal":20,"fppg":47.2,"pos":"G","bench":false,"rk":635,"val":2360,"id":"golf.p.3700$golf.g.2022671 - Scott Gutschewski"},{"name":"Patrick Flavin","sal":22,"fppg":72.6,"pos":"G","bench":false,"rk":646,"val":3300,"id":"golf.p.23285$golf.g.2022671 - Patrick Flavin"},{"name":"Ryan Blaum","sal":20,"fppg":0,"pos":"G","bench":false,"rk":676,"val":0,"id":"golf.p.7293$golf.g.2022671 - Ryan Blaum"},{"name":"Bryson Nimmer","sal":20,"fppg":52.3,"pos":"G","bench":false,"rk":688,"val":2615,"id":"golf.p.23122$golf.g.2022671 - Bryson Nimmer"},{"name":"Aaron Baddeley","sal":21,"fppg":55,"pos":"G","bench":false,"rk":688,"val":2619.05,"id":"golf.p.3175$golf.g.2022671 - Aaron Baddeley"},{"name":"Kelly Kraft","sal":20,"fppg":31.2,"pos":"G","bench":false,"rk":719,"val":1560,"id":"golf.p.11984$golf.g.2022671 - Kelly Kraft"},{"name":"Fabian Gomez","sal":20,"fppg":24.4,"pos":"G","bench":false,"rk":726,"val":1220,"id":"golf.p.9155$golf.g.2022671 - Fabian Gomez"},{"name":"Turk Pettit","sal":20,"fppg":27,"pos":"G","bench":false,"rk":766,"val":1350,"id":"golf.p.24132$golf.g.2022671 - Turk Pettit"},{"name":"Jim Knous","sal":20,"fppg":54.5,"pos":"G","bench":false,"rk":787,"val":2725,"id":"golf.p.12983$golf.g.2022671 - Jim Knous"},{"name":"Grayson Murray","sal":20,"fppg":23.6,"pos":"G","bench":false,"rk":813,"val":1180,"id":"golf.p.11115$golf.g.2022671 - Grayson Murray"},{"name":"David Hearn","sal":20,"fppg":32.5,"pos":"G","bench":false,"rk":867,"val":1625,"id":"golf.p.5725$golf.g.2022671 - David Hearn"},{"name":"Mark Hensby","sal":20,"fppg":54.8,"pos":"G","bench":false,"rk":975,"val":2740,"id":"golf.p.441$golf.g.2022671 - Mark Hensby"},{"name":"Robert Garrigus","sal":22,"fppg":67.4,"pos":"G","bench":false,"rk":1053,"val":3063.64,"id":"golf.p.3458$golf.g.2022671 - Robert Garrigus"},{"name":"Isidro Benitez","sal":20,"fppg":0,"pos":"G","bench":false,"rk":1256,"val":0,"id":"golf.p.22545$golf.g.2022671 - Isidro Benitez"},{"name":"Ricky Barnes","sal":20,"fppg":33.1,"pos":"G","bench":false,"rk":1262,"val":1655,"id":"golf.p.3472$golf.g.2022671 - Ricky Barnes"},{"name":"Jonas Blixt","sal":20,"fppg":25.1,"pos":"G","bench":false,"rk":1337,"val":1255,"id":"golf.p.7182$golf.g.2022671 - Jonas Blixt"},{"name":"Armando Favela","sal":20,"fppg":0,"pos":"G","bench":false,"rk":1383,"val":0,"id":"golf.p.11187$golf.g.2022671 - Armando Favela"},{"name":"D.J. Trahan","sal":20,"fppg":43.3,"pos":"G","bench":false,"rk":1411,"val":2165,"id":"golf.p.2267$golf.g.2022671 - D.J. Trahan"},{"name":"Greg Chalmers","sal":20,"fppg":49.2,"pos":"G","bench":false,"rk":1442,"val":2460,"id":"golf.p.1049$golf.g.2022671 - Greg Chalmers"},{"name":"Johnson Wagner","sal":22,"fppg":62.4,"pos":"G","bench":false,"rk":1468,"val":2836.36,"id":"golf.p.5932$golf.g.2022671 - Johnson Wagner"},{"name":"Derek Ernst","sal":20,"fppg":40,"pos":"G","bench":false,"rk":1545,"val":2000,"id":"golf.p.13096$golf.g.2022671 - Derek Ernst"},{"name":"Arjun Atwal","sal":20,"fppg":42.5,"pos":"G","bench":false,"rk":1679,"val":2125,"id":"golf.p.1830$golf.g.2022671 - Arjun Atwal"},{"name":"Matt Every","sal":20,"fppg":16.6,"pos":"G","bench":false,"rk":1715,"val":830,"id":"golf.p.8060$golf.g.2022671 - Matt Every"},{"name":"Jose Antonio Safa","sal":20,"fppg":0,"pos":"G","bench":false,"rk":1724,"val":0,"id":"golf.p.24239$golf.g.2022671 - Jose Antonio Safa"},{"name":"Jeffrey Kang","sal":20,"fppg":13.6,"pos":"G","bench":false,"rk":1724,"val":680,"id":"golf.p.22629$golf.g.2022671 - Jeffrey Kang"},{"name":"Ben Crane","sal":20,"fppg":23,"pos":"G","bench":false,"rk":1724,"val":1150,"id":"golf.p.3028$golf.g.2022671 - Ben Crane"},{"name":"Ben Willman","sal":20,"fppg":0,"pos":"G","bench":false,"rk":1724,"val":0,"id":"golf.p.5966$golf.g.2022671 - Ben Willman"},{"name":"D.A. Points","sal":20,"fppg":45,"pos":"G","bench":false,"rk":1724,"val":2250,"id":"golf.p.4148$golf.g.2022671 - D.A. Points"},{"name":"Ben Griffin","sal":20,"fppg":0,"pos":"G","bench":false,"rk":2000,"val":0,"id":"golf.p.22821$golf.g.2022671 - Ben Griffin"},{"name":"Manuel Inman","sal":20,"fppg":0,"pos":"G","bench":false,"rk":2000,"val":0,"id":"golf.p.9521$golf.g.2022671 - Manuel Inman"},{"name":"Alvaro Ortiz","sal":20,"fppg":0,"pos":"G","bench":false,"rk":2000,"val":0,"id":"golf.p.20832$golf.g.2022671 - Alvaro Ortiz"},{"name":"Vince Whaley","sal":21,"fppg":55.2,"pos":"G","bench":false,"rk":2000,"val":2628.57,"id":"golf.p.23080$golf.g.2022671 - Vince Whaley"},{"name":"Tyler Duncan","sal":21,"fppg":55.2,"pos":"G","bench":false,"rk":2000,"val":2628.57,"id":"golf.p.18510$golf.g.2022671 - Tyler Duncan"},{"name":"Sung Kang","sal":20,"fppg":45.2,"pos":"G","bench":false,"rk":2000,"val":2260,"id":"golf.p.9583$golf.g.2022671 - Sung Kang"}]}]